<tree> <declarations><attributeDecl name="name" type="String"/> <attributeDecl name="entity" type="String"/><attributeDecl name="tooltip" type="String"/></declarations><branch><attribute name="name" value="entity(4)"/><attribute name="entity" value="http://www.ifomis.org/bfo/1.1#Entity"/><attribute name="tooltip" value="&lt;html>&lt;div style=&quot;font-size:11;width:500&quot;>&lt;b>Class: http://www.ifomis.org/bfo/1.1#Entity&lt;br>&lt;/b>&lt;b>&lt;i>entity&lt;/i>&lt;/b>&lt;i>&lt;br>&lt;/i>&lt;b>super:  &lt;i>&lt;font color=&quot;red&quot;>Thing&lt;/font>&lt;/i>&lt;br>&lt;/b>&lt;font color=&quot;#000080&quot;>(&lt;i>or&lt;/i>&amp;nbsp;continuant&amp;nbsp;occurrent)&lt;br>&lt;/font>&lt;/div>&lt;/html>"/>
<branch><attribute name="name" value="bodily feature of a patient(4)"/><attribute name="entity" value="http://purl.obolibrary.org/obo/OGMS_0000021"/><attribute name="tooltip" value="&lt;html>&lt;div style=&quot;font-size:11;width:500&quot;>&lt;b>Class: http://purl.obolibrary.org/obo/OGMS_0000021&lt;br>&lt;/b>&lt;b>&lt;i>bodily feature of a patient&lt;/i>&lt;/b>&lt;i>&lt;br>&lt;/i>&lt;b>super:  entity&lt;br>&lt;/b>&lt;font color=&quot;#000080&quot;>&lt;/font>&lt;hr>&lt;i>curator note&lt;/i>: creation date: 2009-06-23T11:09:37Z&lt;br>&lt;i>definition editor&lt;/i>: Albert Goldfain&lt;br>&lt;i>editor note&lt;/i>: note: defined class&lt;br>&lt;/div>&lt;/html>"/>
<branch><attribute name="name" value="symptom(1)"/><attribute name="entity" value="http://purl.obolibrary.org/obo/OGMS_0000020"/><attribute name="tooltip" value="&lt;html>&lt;div style=&quot;font-size:11;width:500&quot;>&lt;b>Class: http://purl.obolibrary.org/obo/OGMS_0000020&lt;br>&lt;/b>&lt;b>&lt;i>symptom&lt;/i>&lt;/b>&lt;i>&lt;div style=&quot;margin-left:5px;margin-top:2px;margin-bottom:2px&quot;>A bodily feature of a patient that is observed by the patient and is hypothesized by the patient to be a realization of a disease.&lt;/div>&lt;/i>&lt;b>super:  bodily feature of a patient&lt;br>&lt;/b>&lt;font color=&quot;#000080&quot;>&lt;/font>&lt;hr>&lt;i>curator note&lt;/i>: creation date: 2009-06-23T11:02:10Z&lt;br>&lt;i>definition source&lt;/i>: http://ontology.buffalo.edu/medo/Disease_and_Diagnosis.pdf&lt;br>&lt;i>definition&lt;/i>: A bodily feature of a patient that is observed by the patient and is hypothesized by the patient to be a realization of a disease.&lt;br>&lt;/div>&lt;/html>"/>
<leaf><attribute name="name" value="pain"/><attribute name="entity" value="http://purl.obolibrary.org/obo/OGMS_0000085"/><attribute name="tooltip" value="&lt;html>&lt;div style=&quot;font-size:11;width:500&quot;>&lt;b>Class: http://purl.obolibrary.org/obo/OGMS_0000085&lt;br>&lt;/b>&lt;b>&lt;i>pain&lt;/i>&lt;/b>&lt;i>&lt;div style=&quot;margin-left:5px;margin-top:2px;margin-bottom:2px&quot;>TODO: Define.&lt;/div>&lt;/i>&lt;b>super:  symptom&lt;br>&lt;/b>&lt;font color=&quot;#000080&quot;>&lt;/font>&lt;hr>&lt;i>curator note&lt;/i>: creation date: 2009-11-24T04:51:11Z&lt;br>&lt;i>definition source&lt;/i>: http://code.google.com/p/ogms/issues/detail?id=13&lt;br>&lt;i>definition editor&lt;/i>: Albert Goldfain&lt;br>&lt;i>definition&lt;/i>: TODO: Define.&lt;br>&lt;/div>&lt;/html>"/></leaf>
</branch>
<branch><attribute name="name" value="manifestation of a disease(2)"/><attribute name="entity" value="http://purl.obolibrary.org/obo/OGMS_0000022"/><attribute name="tooltip" value="&lt;html>&lt;div style=&quot;font-size:11;width:500&quot;>&lt;b>Class: http://purl.obolibrary.org/obo/OGMS_0000022&lt;br>&lt;/b>&lt;b>&lt;i>manifestation of a disease&lt;/i>&lt;/b>&lt;i>&lt;div style=&quot;margin-left:5px;margin-top:2px;margin-bottom:2px&quot;>A bodily feature of a patient that is (a) a deviation from clinical normality that exists in virtue of the realization of a disease and (b) is observable.&lt;/div>&lt;/i>&lt;b>super:  bodily feature of a patient&lt;br>&lt;/b>&lt;font color=&quot;#000080&quot;>&lt;/font>&lt;hr>&lt;i>curator note&lt;/i>: creation date: 2009-06-23T11:12:33Z&lt;br>&lt;i>definition source&lt;/i>: http://ontology.buffalo.edu/medo/Disease_and_Diagnosis.pdf&lt;br>&lt;i>definition editor&lt;/i>: Albert Goldfain&lt;br>&lt;i>definition&lt;/i>: A bodily feature of a patient that is (a) a deviation from clinical normality that exists in virtue of the realization of a disease and (b) is observable.&lt;br>&lt;/div>&lt;/html>"/>
<leaf><attribute name="name" value="preclinical manifestationof a disease"/><attribute name="entity" value="http://purl.obolibrary.org/obo/OGMS_0000026"/><attribute name="tooltip" value="&lt;html>&lt;div style=&quot;font-size:11;width:500&quot;>&lt;b>Class: http://purl.obolibrary.org/obo/OGMS_0000026&lt;br>&lt;/b>&lt;b>&lt;i>preclinical manifestationof a disease&lt;/i>&lt;/b>&lt;i>&lt;div style=&quot;margin-left:5px;margin-top:2px;margin-bottom:2px&quot;>A manifestation of a disease that exists prior to the time at which it would be detected in a clinical history taking or physical examination, if the patient were to present to a clinician. A realization of a disease that exists prior to its becoming detectable in a clinical history taking or physical examination.&lt;/div>&lt;/i>&lt;b>super:  manifestation of a disease&lt;br>&lt;/b>&lt;font color=&quot;#000080&quot;>&lt;/font>&lt;hr>&lt;i>curator note&lt;/i>: creation date: 2009-06-23T11:16:50Z&lt;br>&lt;i>definition source&lt;/i>: http://ontology.buffalo.edu/medo/Disease_and_Diagnosis.pdf&lt;br>&lt;i>definition editor&lt;/i>: Albert Goldfain&lt;br>&lt;i>definition&lt;/i>: A manifestation of a disease that exists prior to the time at which it would be detected in a clinical history taking or physical examination, if the patient were to present to a clinician. A realization of a disease that exists prior to its becoming detectable in a clinical history taking or physical examination.&lt;br>&lt;/div>&lt;/html>"/></leaf>
<leaf><attribute name="name" value="clinical manifestation of a disease"/><attribute name="entity" value="http://purl.obolibrary.org/obo/OGMS_0000025"/><attribute name="tooltip" value="&lt;html>&lt;div style=&quot;font-size:11;width:500&quot;>&lt;b>Class: http://purl.obolibrary.org/obo/OGMS_0000025&lt;br>&lt;/b>&lt;b>&lt;i>clinical manifestation of a disease&lt;/i>&lt;/b>&lt;i>&lt;div style=&quot;margin-left:5px;margin-top:2px;margin-bottom:2px&quot;>A manifestation of a disease that is detectable in a clinical history taking or physical examination.&lt;/div>&lt;/i>&lt;b>super:  manifestation of a disease&lt;br>&lt;/b>&lt;font color=&quot;#000080&quot;>&lt;/font>&lt;hr>&lt;i>curator note&lt;/i>: creation date: 2009-06-23T11:15:43Z&lt;br>&lt;i>definition source&lt;/i>: http://ontology.buffalo.edu/medo/Disease_and_Diagnosis.pdf&lt;br>&lt;i>definition editor&lt;/i>: Albert Goldfain&lt;br>&lt;i>definition&lt;/i>: A manifestation of a disease that is detectable in a clinical history taking or physical examination.&lt;br>&lt;/div>&lt;/html>"/></leaf>
</branch>
<branch><attribute name="name" value="phenotype(2)"/><attribute name="entity" value="http://purl.obolibrary.org/obo/OGMS_0000023"/><attribute name="tooltip" value="&lt;html>&lt;div style=&quot;font-size:11;width:500&quot;>&lt;b>Class: http://purl.obolibrary.org/obo/OGMS_0000023&lt;br>&lt;/b>&lt;b>&lt;i>phenotype&lt;/i>&lt;/b>&lt;i>&lt;div style=&quot;margin-left:5px;margin-top:2px;margin-bottom:2px&quot;>A (combination of) bodily feature(s) of an organism determined by the interaction of its genetic make-up and environment that differentiates specific instances of a species from other instances of the same species.&lt;/div>&lt;/i>&lt;b>super:  bodily feature of a patient&lt;br>&lt;/b>&lt;font color=&quot;#000080&quot;>&lt;/font>&lt;hr>&lt;i>curator note&lt;/i>: creation date: 2009-06-23T11:13:49Z&lt;br>&lt;i>definition source&lt;/i>: http://ontology.buffalo.edu/medo/Disease_and_Diagnosis.pdf&lt;br>&lt;i>definition editor&lt;/i>: Albert Goldfain&lt;br>&lt;i>definition&lt;/i>: A (combination of) bodily feature(s) of an organism determined by the interaction of its genetic make-up and environment that differentiates specific instances of a species from other instances of the same species.&lt;br>&lt;/div>&lt;/html>"/>
<leaf><attribute name="name" value="clinical phenotype"/><attribute name="entity" value="http://purl.obolibrary.org/obo/OGMS_0000027"/><attribute name="tooltip" value="&lt;html>&lt;div style=&quot;font-size:11;width:500&quot;>&lt;b>Class: http://purl.obolibrary.org/obo/OGMS_0000027&lt;br>&lt;/b>&lt;b>&lt;i>clinical phenotype&lt;/i>&lt;/b>&lt;i>&lt;div style=&quot;margin-left:5px;margin-top:2px;margin-bottom:2px&quot;>A clinically abnormal phenotype.&lt;/div>&lt;/i>&lt;b>super:  phenotype&lt;br>&lt;/b>&lt;font color=&quot;#000080&quot;>&lt;/font>&lt;hr>&lt;i>curator note&lt;/i>: creation date: 2009-06-23T11:18:05Z&lt;br>&lt;i>definition source&lt;/i>: http://ontology.buffalo.edu/medo/Disease_and_Diagnosis.pdf&lt;br>&lt;i>definition editor&lt;/i>: Albert Goldfain&lt;br>&lt;i>definition&lt;/i>: A clinically abnormal phenotype.&lt;br>&lt;/div>&lt;/html>"/></leaf>
<leaf><attribute name="name" value="disease phenotype"/><attribute name="entity" value="http://purl.obolibrary.org/obo/OGMS_0000028"/><attribute name="tooltip" value="&lt;html>&lt;div style=&quot;font-size:11;width:500&quot;>&lt;b>Class: http://purl.obolibrary.org/obo/OGMS_0000028&lt;br>&lt;/b>&lt;b>&lt;i>disease phenotype&lt;/i>&lt;/b>&lt;i>&lt;div style=&quot;margin-left:5px;margin-top:2px;margin-bottom:2px&quot;>A clinically abnormal phenotype that is characteristic of a single disease.&lt;/div>&lt;/i>&lt;b>super:  phenotype&lt;br>&lt;/b>&lt;font color=&quot;#000080&quot;>&lt;/font>&lt;hr>&lt;i>curator note&lt;/i>: creation date: 2009-06-23T11:18:39Z&lt;br>&lt;i>definition source&lt;/i>: http://ontology.buffalo.edu/medo/Disease_and_Diagnosis.pdf&lt;br>&lt;i>definition editor&lt;/i>: Albert Goldfain&lt;br>&lt;i>definition&lt;/i>: A clinically abnormal phenotype that is characteristic of a single disease.&lt;br>&lt;/div>&lt;/html>"/></leaf>
</branch>
<branch><attribute name="name" value="sign(1)"/><attribute name="entity" value="http://purl.obolibrary.org/obo/OGMS_0000024"/><attribute name="tooltip" value="&lt;html>&lt;div style=&quot;font-size:11;width:500&quot;>&lt;b>Class: http://purl.obolibrary.org/obo/OGMS_0000024&lt;br>&lt;/b>&lt;b>&lt;i>sign&lt;/i>&lt;/b>&lt;i>&lt;div style=&quot;margin-left:5px;margin-top:2px;margin-bottom:2px&quot;>A bodily feature of a patient that is observed in a physical examination and is deemed by the clinician to be of clinical significance.&lt;/div>&lt;/i>&lt;b>super:  bodily feature of a patient&lt;br>&lt;/b>&lt;font color=&quot;#000080&quot;>&lt;/font>&lt;hr>&lt;i>curator note&lt;/i>: creation date: 2009-06-23T11:14:36Z&lt;br>&lt;i>definition source&lt;/i>: http://ontology.buffalo.edu/medo/Disease_and_Diagnosis.pdf&lt;br>&lt;i>definition editor&lt;/i>: Albert Goldfain&lt;br>&lt;i>definition&lt;/i>: A bodily feature of a patient that is observed in a physical examination and is deemed by the clinician to be of clinical significance.&lt;br>&lt;/div>&lt;/html>"/>
<leaf><attribute name="name" value="vital sign"/><attribute name="entity" value="http://purl.obolibrary.org/obo/OGMS_0000029"/><attribute name="tooltip" value="&lt;html>&lt;div style=&quot;font-size:11;width:500&quot;>&lt;b>Class: http://purl.obolibrary.org/obo/OGMS_0000029&lt;br>&lt;/b>&lt;b>&lt;i>vital sign&lt;/i>&lt;/b>&lt;i>&lt;div style=&quot;margin-left:5px;margin-top:2px;margin-bottom:2px&quot;>A physical sign in which a non-zero value is standardly considered to be an indication that the organism is alive.&lt;/div>&lt;/i>&lt;b>super:  sign&lt;br>&lt;/b>&lt;font color=&quot;#000080&quot;>&lt;/font>&lt;hr>&lt;i>curator note&lt;/i>: creation date: 2009-06-23T11:19:17Z&lt;br>&lt;i>definition source&lt;/i>: http://ontology.buffalo.edu/medo/Disease_and_Diagnosis.pdf&lt;br>&lt;i>definition editor&lt;/i>: Albert Goldfain&lt;br>&lt;i>definition&lt;/i>: A physical sign in which a non-zero value is standardly considered to be an indication that the organism is alive.&lt;br>&lt;/div>&lt;/html>"/></leaf>
</branch>
</branch>
<branch><attribute name="name" value="occurrent(3)"/><attribute name="entity" value="http://www.ifomis.org/bfo/1.1/span#Occurrent"/><attribute name="tooltip" value="&lt;html>&lt;div style=&quot;font-size:11;width:500&quot;>&lt;b>Class: http://www.ifomis.org/bfo/1.1/span#Occurrent&lt;br>&lt;/b>&lt;b>&lt;i>occurrent&lt;/i>&lt;/b>&lt;i>&lt;div style=&quot;margin-left:5px;margin-top:2px;margin-bottom:2px&quot;>Synonyms: perdurant; Examples: the life of an organism, a surgical operation as processual context for a nosocomical infection, the spatiotemporal context occupied by a process of cellular meiosis, the most interesting part of Van Gogh's life, the spatiotemporal region occupied by the development of a cancer tumor; Definition: An entity [bfo:Entity] that has temporal parts and that happens, unfolds or develops through time. Sometimes also called perdurants.&lt;/div>&lt;/i>&lt;b>super:  entity&lt;br>&lt;/b>&lt;font color=&quot;#000080&quot;>(&lt;i>and&lt;/i>&amp;nbsp;entity&amp;nbsp;(&lt;i>or&lt;/i>&amp;nbsp;processual_entity&amp;nbsp;spatiotemporal_region&amp;nbsp;temporal_region))&lt;br>&lt;/font>&lt;/div>&lt;/html>"/>
<branch><attribute name="name" value="processual_entity(5)"/><attribute name="entity" value="http://www.ifomis.org/bfo/1.1/span#ProcessualEntity"/><attribute name="tooltip" value="&lt;html>&lt;div style=&quot;font-size:11;width:500&quot;>&lt;b>Class: http://www.ifomis.org/bfo/1.1/span#ProcessualEntity&lt;br>&lt;/b>&lt;b>&lt;i>processual_entity&lt;/i>&lt;/b>&lt;i>&lt;div style=&quot;margin-left:5px;margin-top:2px;margin-bottom:2px&quot;>Examples: the life of an organism, the process of meiosis, the course of a disease, the flight of a bird; Definition: An occurrent [span:Occurrent] that exists in time by occurring or happening, has temporal parts and always involves and depends on some entity.&lt;/div>&lt;/i>&lt;b>super:  occurrent&lt;br>&lt;/b>&lt;font color=&quot;#000080&quot;>(&lt;i>and&lt;/i>&amp;nbsp;occurrent&lt;br>&amp;nbsp;(&lt;i>or&lt;/i>&amp;nbsp;fiat_process_part&amp;nbsp;process&amp;nbsp;process_aggregate&amp;nbsp;process_boundary&lt;br>&amp;nbsp;&amp;nbsp;processual_context)&lt;br>&amp;nbsp;(&lt;i>disjoint-with&lt;/i>&amp;nbsp;spatiotemporal_region&amp;nbsp;temporal_region))&lt;br>&lt;/font>&lt;/div>&lt;/html>"/>
<branch><attribute name="name" value="process(2)"/><attribute name="entity" value="http://www.ifomis.org/bfo/1.1/span#Process"/><attribute name="tooltip" value="&lt;html>&lt;div style=&quot;font-size:11;width:500&quot;>&lt;b>Class: http://www.ifomis.org/bfo/1.1/span#Process&lt;br>&lt;/b>&lt;b>&lt;i>process&lt;/i>&lt;/b>&lt;i>&lt;div style=&quot;margin-left:5px;margin-top:2px;margin-bottom:2px&quot;>Examples: the life of an organism, the process of sleeping, the process of cell-division; Definition: A processual entity [span:ProcessualEntity] that is a maximally connected spatiotemporal whole and has bona fide beginnings and endings corresponding to real discontinuities.&lt;/div>&lt;/i>&lt;b>super:  processual_entity&lt;br>&lt;/b>&lt;font color=&quot;#000080&quot;>(&lt;i>and&lt;/i>&amp;nbsp;processual_entity&lt;br>&amp;nbsp;(&lt;i>disjoint-with&lt;/i>&amp;nbsp;processual_context&amp;nbsp;process_boundary&amp;nbsp;process_aggregate&lt;br>&amp;nbsp;&amp;nbsp;fiat_process_part))&lt;br>&lt;/font>&lt;/div>&lt;/html>"/>
<leaf><attribute name="name" value="etiological process"/><attribute name="entity" value="http://purl.obolibrary.org/obo/OGMS_0000059"/><attribute name="tooltip" value="&lt;html>&lt;div style=&quot;font-size:11;width:500&quot;>&lt;b>Class: http://purl.obolibrary.org/obo/OGMS_0000059&lt;br>&lt;/b>&lt;b>&lt;i>etiological process&lt;/i>&lt;/b>&lt;i>&lt;div style=&quot;margin-left:5px;margin-top:2px;margin-bottom:2px&quot;>A process in an organism that leads to a subsequent disorder.&lt;/div>&lt;/i>&lt;b>super:  process&lt;br>&lt;/b>&lt;font color=&quot;#000080&quot;>&lt;/font>&lt;hr>&lt;i>curator note&lt;/i>: creation date: 2009-06-23T11:53:07Z&lt;br>&lt;i>definition source&lt;/i>: http://ontology.buffalo.edu/medo/Disease_and_Diagnosis.pdf&lt;br>&lt;i>definition editor&lt;/i>: Albert Goldfain&lt;br>&lt;i>definition&lt;/i>: A process in an organism that leads to a subsequent disorder.&lt;br>&lt;/div>&lt;/html>"/></leaf>
<branch><attribute name="name" value="bodily process(1)"/><attribute name="entity" value="http://purl.obolibrary.org/obo/OGMS_0000060"/><attribute name="tooltip" value="&lt;html>&lt;div style=&quot;font-size:11;width:500&quot;>&lt;b>Class: http://purl.obolibrary.org/obo/OGMS_0000060&lt;br>&lt;/b>&lt;b>&lt;i>bodily process&lt;/i>&lt;/b>&lt;i>&lt;br>&lt;/i>&lt;b>super:  process&lt;br>&lt;/b>&lt;font color=&quot;#000080&quot;>&lt;/font>&lt;hr>&lt;i>curator note&lt;/i>: creation date: 2009-06-23T11:53:49Z&lt;br>&lt;i>definition editor&lt;/i>: Albert Goldfain&lt;br>&lt;/div>&lt;/html>"/>
<branch><attribute name="name" value="pathological bodily process(3)"/><attribute name="entity" value="http://purl.obolibrary.org/obo/OGMS_0000061"/><attribute name="tooltip" value="&lt;html>&lt;div style=&quot;font-size:11;width:500&quot;>&lt;b>Class: http://purl.obolibrary.org/obo/OGMS_0000061&lt;br>&lt;/b>&lt;b>&lt;i>pathological bodily process&lt;/i>&lt;/b>&lt;i>&lt;div style=&quot;margin-left:5px;margin-top:2px;margin-bottom:2px&quot;>A bodily process that is clinically abnormal.&lt;/div>&lt;/i>&lt;b>super:  bodily process&lt;br>&lt;/b>&lt;font color=&quot;#000080&quot;>&lt;/font>&lt;hr>&lt;i>curator note&lt;/i>: creation date: 2009-06-23T11:54:29Z&lt;br>&lt;i>definition source&lt;/i>: http://ontology.buffalo.edu/medo/Disease_and_Diagnosis.pdf&lt;br>&lt;i>definition editor&lt;/i>: Albert Goldfain&lt;br>&lt;i>definition&lt;/i>: A bodily process that is clinically abnormal.&lt;br>&lt;/div>&lt;/html>"/>
<leaf><attribute name="name" value="pathological derivation"/><attribute name="entity" value="http://purl.obolibrary.org/obo/OGMS_0000081"/><attribute name="tooltip" value="&lt;html>&lt;div style=&quot;font-size:11;width:500&quot;>&lt;b>Class: http://purl.obolibrary.org/obo/OGMS_0000081&lt;br>&lt;/b>&lt;b>&lt;i>pathological derivation&lt;/i>&lt;/b>&lt;i>&lt;div style=&quot;margin-left:5px;margin-top:2px;margin-bottom:2px&quot;>A pathological bodily process in which matter is reorganized in such a way as to give rise to new pathological formations which take the place of entities existing earlier.&lt;/div>&lt;/i>&lt;b>super:  pathological bodily process&lt;br>&lt;/b>&lt;font color=&quot;#000080&quot;>&lt;/font>&lt;hr>&lt;i>curator note&lt;/i>: creation date: 2009-07-13T02:17:24Z&lt;br>&lt;i>definition source&lt;/i>: http://ontology.buffalo.edu/bio/ISMB/ISMB_Bio-ontologies.pdf&lt;br>&lt;i>definition editor&lt;/i>: Albert Goldfain&lt;br>&lt;i>definition&lt;/i>: A pathological bodily process in which matter is reorganized in such a way as to give rise to new pathological formations which take the place of entities existing earlier.&lt;br>&lt;/div>&lt;/html>"/></leaf>
<leaf><attribute name="name" value="pathological transformation"/><attribute name="entity" value="http://purl.obolibrary.org/obo/OGMS_0000080"/><attribute name="tooltip" value="&lt;html>&lt;div style=&quot;font-size:11;width:500&quot;>&lt;b>Class: http://purl.obolibrary.org/obo/OGMS_0000080&lt;br>&lt;/b>&lt;b>&lt;i>pathological transformation&lt;/i>&lt;/b>&lt;i>&lt;div style=&quot;margin-left:5px;margin-top:2px;margin-bottom:2px&quot;>A pathological bodily process in which a canonical anatomical structure becomes a pathological anatomical structure.&lt;/div>&lt;/i>&lt;b>super:  pathological bodily process&lt;br>&lt;/b>&lt;font color=&quot;#000080&quot;>&lt;/font>&lt;hr>&lt;i>curator note&lt;/i>: creation date: 2009-07-13T02:17:07Z&lt;br>&lt;i>definition source&lt;/i>: http://ontology.buffalo.edu/bio/ISMB/ISMB_Bio-ontologies.pdf&lt;br>&lt;i>definition editor&lt;/i>: Albert Goldfain&lt;br>&lt;i>definition&lt;/i>: A pathological bodily process in which a canonical anatomical structure becomes a pathological anatomical structure.&lt;br>&lt;/div>&lt;/html>"/></leaf>
<leaf><attribute name="name" value="pathological invasion"/><attribute name="entity" value="http://purl.obolibrary.org/obo/OGMS_0000082"/><attribute name="tooltip" value="&lt;html>&lt;div style=&quot;font-size:11;width:500&quot;>&lt;b>Class: http://purl.obolibrary.org/obo/OGMS_0000082&lt;br>&lt;/b>&lt;b>&lt;i>pathological invasion&lt;/i>&lt;/b>&lt;i>&lt;div style=&quot;margin-left:5px;margin-top:2px;margin-bottom:2px&quot;>TODO: Define.&lt;/div>&lt;/i>&lt;b>super:  pathological bodily process&lt;br>&lt;/b>&lt;font color=&quot;#000080&quot;>&lt;/font>&lt;hr>&lt;i>curator note&lt;/i>: creation date: 2009-07-13T02:17:47Z&lt;br>&lt;i>definition source&lt;/i>: http://ontology.buffalo.edu/bio/ISMB/ISMB_Bio-ontologies.pdf&lt;br>&lt;i>definition editor&lt;/i>: Albert Goldfain&lt;br>&lt;i>definition&lt;/i>: TODO: Define.&lt;br>&lt;/div>&lt;/html>"/></leaf>
</branch>
</branch>
</branch>
<leaf><attribute name="name" value="process_boundary"/><attribute name="entity" value="http://www.ifomis.org/bfo/1.1/span#ProcessBoundary"/><attribute name="tooltip" value="&lt;html>&lt;div style=&quot;font-size:11;width:500&quot;>&lt;b>Class: http://www.ifomis.org/bfo/1.1/span#ProcessBoundary&lt;br>&lt;/b>&lt;b>&lt;i>process_boundary&lt;/i>&lt;/b>&lt;i>&lt;div style=&quot;margin-left:5px;margin-top:2px;margin-bottom:2px&quot;>Examples: birth, death, the forming of a synapse, the onset of REM sleep, the detaching of a finger in an industrial accident, the final separation of two cells at the end of cell-division, the incision at the beginning of a surgery; Definition: A processual entity [span:ProcessualEntity] that is the fiat or bona fide instantaneous temporal process boundary.&lt;/div>&lt;/i>&lt;b>super:  processual_entity&lt;br>&lt;/b>&lt;font color=&quot;#000080&quot;>&lt;/font>&lt;/div>&lt;/html>"/></leaf>
<branch><attribute name="name" value="fiat_process_part(3)"/><attribute name="entity" value="http://www.ifomis.org/bfo/1.1/span#FiatProcessPart"/><attribute name="tooltip" value="&lt;html>&lt;div style=&quot;font-size:11;width:500&quot;>&lt;b>Class: http://www.ifomis.org/bfo/1.1/span#FiatProcessPart&lt;br>&lt;/b>&lt;b>&lt;i>fiat_process_part&lt;/i>&lt;/b>&lt;i>&lt;div style=&quot;margin-left:5px;margin-top:2px;margin-bottom:2px&quot;>Examples: chewing during a meal, the middle part of a rainstorm, the worst part of a heart-attack, the most interesting part of Van Gogh's life; Definition: A processual entity [span:ProcessualEntity] that is part of a process but that does not have bona fide beginnings and endings corresponding to real discontinuities.&lt;/div>&lt;/i>&lt;b>super:  processual_entity&lt;br>&lt;/b>&lt;font color=&quot;#000080&quot;>(&lt;i>and&lt;/i>&amp;nbsp;processual_entity&amp;nbsp;(&lt;i>disjoint-with&lt;/i>&amp;nbsp;process_boundary&amp;nbsp;process))&lt;br>&lt;/font>&lt;/div>&lt;/html>"/>
<leaf><attribute name="name" value="clinical history taking"/><attribute name="entity" value="http://purl.obolibrary.org/obo/OGMS_0000055"/><attribute name="tooltip" value="&lt;html>&lt;div style=&quot;font-size:11;width:500&quot;>&lt;b>Class: http://purl.obolibrary.org/obo/OGMS_0000055&lt;br>&lt;/b>&lt;b>&lt;i>clinical history taking&lt;/i>&lt;/b>&lt;i>&lt;div style=&quot;margin-left:5px;margin-top:2px;margin-bottom:2px&quot;>An interview in which a clinician elicits a clinical history from a patient or from a third party who is reporting on behalf of the patient.&lt;/div>&lt;/i>&lt;b>super:  fiat_process_part&lt;br>&lt;/b>&lt;font color=&quot;#000080&quot;>&lt;/font>&lt;hr>&lt;i>curator note&lt;/i>: creation date: 2009-06-23T11:49:16Z&lt;br>&lt;i>definition source&lt;/i>: http://ontology.buffalo.edu/medo/Disease_and_Diagnosis.pdf&lt;br>&lt;i>definition editor&lt;/i>: Albert Goldfain&lt;br>&lt;i>definition&lt;/i>: An interview in which a clinician elicits a clinical history from a patient or from a third party who is reporting on behalf of the patient.&lt;br>&lt;/div>&lt;/html>"/></leaf>
<leaf><attribute name="name" value="laboratory test"/><attribute name="entity" value="http://purl.obolibrary.org/obo/OGMS_0000056"/><attribute name="tooltip" value="&lt;html>&lt;div style=&quot;font-size:11;width:500&quot;>&lt;b>Class: http://purl.obolibrary.org/obo/OGMS_0000056&lt;br>&lt;/b>&lt;b>&lt;i>laboratory test&lt;/i>&lt;/b>&lt;i>&lt;div style=&quot;margin-left:5px;margin-top:2px;margin-bottom:2px&quot;>A measurement assay that has as input a patient-derived specimen, and as output a result that represents a quality of the specimen.&lt;/div>&lt;/i>&lt;b>super:  fiat_process_part&lt;br>&lt;/b>&lt;font color=&quot;#000080&quot;>&lt;/font>&lt;hr>&lt;i>curator note&lt;/i>: creation date: 2009-06-23T11:49:49Z&lt;br>&lt;i>definition source&lt;/i>: http://ontology.buffalo.edu/medo/Disease_and_Diagnosis.pdf&lt;br>&lt;i>definition editor&lt;/i>: Albert Goldfain&lt;br>&lt;i>definition&lt;/i>: A measurement assay that has as input a patient-derived specimen, and as output a result that represents a quality of the specimen.&lt;br>&lt;/div>&lt;/html>"/></leaf>
<leaf><attribute name="name" value="physical examination"/><attribute name="entity" value="http://purl.obolibrary.org/obo/OGMS_0000057"/><attribute name="tooltip" value="&lt;html>&lt;div style=&quot;font-size:11;width:500&quot;>&lt;b>Class: http://purl.obolibrary.org/obo/OGMS_0000057&lt;br>&lt;/b>&lt;b>&lt;i>physical examination&lt;/i>&lt;/b>&lt;i>&lt;div style=&quot;margin-left:5px;margin-top:2px;margin-bottom:2px&quot;>A sequence of acts of observing and measuring bodily features of a patient performed by a clinician; measurements may occur with and without elicitation.&lt;/div>&lt;/i>&lt;b>super:  fiat_process_part&lt;br>&lt;/b>&lt;font color=&quot;#000080&quot;>&lt;/font>&lt;hr>&lt;i>curator note&lt;/i>: creation date: 2009-06-23T11:50:18Z&lt;br>&lt;i>definition source&lt;/i>: http://ontology.buffalo.edu/medo/Disease_and_Diagnosis.pdf&lt;br>&lt;i>definition editor&lt;/i>: Albert Goldfain&lt;br>&lt;i>definition&lt;/i>: A sequence of acts of observing and measuring bodily features of a patient performed by a clinician; measurements may occur with and without elicitation.&lt;br>&lt;/div>&lt;/html>"/></leaf>
</branch>
<branch><attribute name="name" value="process_aggregate(1)"/><attribute name="entity" value="http://www.ifomis.org/bfo/1.1/span#ProcessAggregate"/><attribute name="tooltip" value="&lt;html>&lt;div style=&quot;font-size:11;width:500&quot;>&lt;b>Class: http://www.ifomis.org/bfo/1.1/span#ProcessAggregate&lt;br>&lt;/b>&lt;b>&lt;i>process_aggregate&lt;/i>&lt;/b>&lt;i>&lt;div style=&quot;margin-left:5px;margin-top:2px;margin-bottom:2px&quot;>Examples: the beating of the hearts of each of seven individuals in the room, the playing of each of the members of an orchestra, a process of digestion and a process of thinking taken together; Definition: A processual entity [span:ProcessualEntity] that is a mereological sum of process [span:Process] entities and possesses non-connected boundaries.&lt;/div>&lt;/i>&lt;b>super:  processual_entity&lt;br>&lt;/b>&lt;font color=&quot;#000080&quot;>(&lt;i>and&lt;/i>&amp;nbsp;processual_entity&lt;br>&amp;nbsp;(&lt;i>disjoint-with&lt;/i>&amp;nbsp;processual_context&amp;nbsp;process_boundary&amp;nbsp;fiat_process_part&amp;nbsp;process))&lt;br>&lt;/font>&lt;/div>&lt;/html>"/>
<branch><attribute name="name" value="disease course(3)"/><attribute name="entity" value="http://purl.obolibrary.org/obo/OGMS_0000063"/><attribute name="tooltip" value="&lt;html>&lt;div style=&quot;font-size:11;width:500&quot;>&lt;b>Class: http://purl.obolibrary.org/obo/OGMS_0000063&lt;br>&lt;/b>&lt;b>&lt;i>disease course&lt;/i>&lt;/b>&lt;i>&lt;div style=&quot;margin-left:5px;margin-top:2px;margin-bottom:2px&quot;>The totality of all processes through which a given disease instance is realized.&lt;/div>&lt;/i>&lt;b>super:  process_aggregate&lt;br>&lt;/b>&lt;font color=&quot;#000080&quot;>&lt;/font>&lt;hr>&lt;i>curator note&lt;/i>: creation date: 2009-06-23T11:55:44Z&lt;br>&lt;i>definition source&lt;/i>: http://ontology.buffalo.edu/medo/Disease_and_Diagnosis.pdf&lt;br>&lt;i>definition editor&lt;/i>: Albert Goldfain&lt;br>&lt;i>definition&lt;/i>: The totality of all processes through which a given disease instance is realized.&lt;br>&lt;/div>&lt;/html>"/>
<leaf><attribute name="name" value="transient disease course"/><attribute name="entity" value="http://purl.obolibrary.org/obo/OGMS_0000066"/><attribute name="tooltip" value="&lt;html>&lt;div style=&quot;font-size:11;width:500&quot;>&lt;b>Class: http://purl.obolibrary.org/obo/OGMS_0000066&lt;br>&lt;/b>&lt;b>&lt;i>transient disease course&lt;/i>&lt;/b>&lt;i>&lt;div style=&quot;margin-left:5px;margin-top:2px;margin-bottom:2px&quot;>A disease course that terminates in a return to normal homeostasis.&lt;/div>&lt;/i>&lt;b>super:  disease course&lt;br>&lt;/b>&lt;font color=&quot;#000080&quot;>&lt;/font>&lt;hr>&lt;i>curator note&lt;/i>: creation date: 2009-06-23T11:57:44Z&lt;br>&lt;i>definition source&lt;/i>: http://ontology.buffalo.edu/medo/Disease_and_Diagnosis.pdf&lt;br>&lt;i>definition editor&lt;/i>: Albert Goldfain&lt;br>&lt;i>definition&lt;/i>: A disease course that terminates in a return to normal homeostasis.&lt;br>&lt;/div>&lt;/html>"/></leaf>
<leaf><attribute name="name" value="progressive disease course"/><attribute name="entity" value="http://purl.obolibrary.org/obo/OGMS_0000065"/><attribute name="tooltip" value="&lt;html>&lt;div style=&quot;font-size:11;width:500&quot;>&lt;b>Class: http://purl.obolibrary.org/obo/OGMS_0000065&lt;br>&lt;/b>&lt;b>&lt;i>progressive disease course&lt;/i>&lt;/b>&lt;i>&lt;div style=&quot;margin-left:5px;margin-top:2px;margin-bottom:2px&quot;>A disease course that (a) does not terminate in a return to normal homeostasis and (b) would, absent intervention, involve an increasing deviation from homeostasis.&lt;/div>&lt;/i>&lt;b>super:  disease course&lt;br>&lt;/b>&lt;font color=&quot;#000080&quot;>&lt;/font>&lt;hr>&lt;i>curator note&lt;/i>: creation date: 2009-06-23T11:57:09Z&lt;br>&lt;i>definition source&lt;/i>: http://ontology.buffalo.edu/medo/Disease_and_Diagnosis.pdf&lt;br>&lt;i>definition editor&lt;/i>: Albert Goldfain&lt;br>&lt;i>definition&lt;/i>: A disease course that (a) does not terminate in a return to normal homeostasis and (b) would, absent intervention, involve an increasing deviation from homeostasis.&lt;br>&lt;/div>&lt;/html>"/></leaf>
<leaf><attribute name="name" value="chronic disease course"/><attribute name="entity" value="http://purl.obolibrary.org/obo/OGMS_0000064"/><attribute name="tooltip" value="&lt;html>&lt;div style=&quot;font-size:11;width:500&quot;>&lt;b>Class: http://purl.obolibrary.org/obo/OGMS_0000064&lt;br>&lt;/b>&lt;b>&lt;i>chronic disease course&lt;/i>&lt;/b>&lt;i>&lt;div style=&quot;margin-left:5px;margin-top:2px;margin-bottom:2px&quot;>A disease course that (a) does not terminate in a return to normal homeostasis and (b) would, absent intervention, fall within abnormal homeostatic range.&lt;/div>&lt;/i>&lt;b>super:  disease course&lt;br>&lt;/b>&lt;font color=&quot;#000080&quot;>&lt;/font>&lt;hr>&lt;i>curator note&lt;/i>: creation date: 2009-06-23T11:56:26Z&lt;br>&lt;i>definition source&lt;/i>: http://ontology.buffalo.edu/medo/Disease_and_Diagnosis.pdf&lt;br>&lt;i>definition editor&lt;/i>: Albert Goldfain&lt;br>&lt;i>definition&lt;/i>: A disease course that (a) does not terminate in a return to normal homeostasis and (b) would, absent intervention, fall within abnormal homeostatic range.&lt;br>&lt;/div>&lt;/html>"/></leaf>
</branch>
</branch>
<leaf><attribute name="name" value="processual_context"/><attribute name="entity" value="http://www.ifomis.org/bfo/1.1/span#ProcessualContext"/><attribute name="tooltip" value="&lt;html>&lt;div style=&quot;font-size:11;width:500&quot;>&lt;b>Class: http://www.ifomis.org/bfo/1.1/span#ProcessualContext&lt;br>&lt;/b>&lt;b>&lt;i>processual_context&lt;/i>&lt;/b>&lt;i>&lt;div style=&quot;margin-left:5px;margin-top:2px;margin-bottom:2px&quot;>Comment: An instance of a processual context [span:ProcessualContext] is a mixture of processual entity [span:ProcessualEntity] which stand as surrounding environments for other processual entity [span:ProcessualEntity] entities. The class processual context [span:ProcessualContext] is the analogous among occurrent [span:Occurrent] entities to the class site [snap:Site] among continuant [snap:Continuant] entities.; Examples: The processual context for a given manipulation occurring as part of an experiment is made of processual entities which occur in parallel, are not necessarily all parts of the experiment themselves and may involve continuant [snap:Continuant] entities which are in the spatial vicinity of the participants in the experiment.; Definition: An occurrent [span:Occurrent] consisting of a characteristic spatial shape inhering in some arrangement of other occurrent [span:Occurrent] entities. Processual context [span:ProcessualContext] entities are characteristically entities at or in which other occurrent [span:Occurrent] entities can be located or occur.&lt;/div>&lt;/i>&lt;b>super:  processual_entity&lt;br>&lt;/b>&lt;font color=&quot;#000080&quot;>(&lt;i>and&lt;/i>&amp;nbsp;processual_entity&lt;br>&amp;nbsp;(&lt;i>disjoint-with&lt;/i>&amp;nbsp;fiat_process_part&amp;nbsp;process_boundary&amp;nbsp;process))&lt;br>&lt;/font>&lt;/div>&lt;/html>"/></leaf>
</branch>
</branch>
<branch><attribute name="name" value="continuant(3)"/><attribute name="entity" value="http://www.ifomis.org/bfo/1.1/snap#Continuant"/><attribute name="tooltip" value="&lt;html>&lt;div style=&quot;font-size:11;width:500&quot;>&lt;b>Class: http://www.ifomis.org/bfo/1.1/snap#Continuant&lt;br>&lt;/b>&lt;b>&lt;i>continuant&lt;/i>&lt;/b>&lt;i>&lt;div style=&quot;margin-left:5px;margin-top:2px;margin-bottom:2px&quot;>Synonyms: endurant; Examples: a heart, a person, the color of a tomato, the mass of a cloud, a symphony orchestra, the disposition of blood to coagulate, the lawn and atmosphere in front of our building; Definition: An entity [bfo:Entity] that exists in full at any time in which it exists at all, persists through time while maintaining its identity and has no temporal parts.&lt;/div>&lt;/i>&lt;b>super:  entity&lt;br>&lt;/b>&lt;font color=&quot;#000080&quot;>(&lt;i>and&lt;/i>&amp;nbsp;(&lt;i>not&lt;/i>&amp;nbsp;occurrent)&amp;nbsp;entity&lt;br>&amp;nbsp;(&lt;i>or&lt;/i>&amp;nbsp;dependent_continuant&amp;nbsp;independent_continuant&amp;nbsp;spatial_region))&lt;br>&lt;/font>&lt;/div>&lt;/html>"/>
<branch><attribute name="name" value="dependent_continuant(2)"/><attribute name="entity" value="http://www.ifomis.org/bfo/1.1/snap#DependentContinuant"/><attribute name="tooltip" value="&lt;html>&lt;div style=&quot;font-size:11;width:500&quot;>&lt;b>Class: http://www.ifomis.org/bfo/1.1/snap#DependentContinuant&lt;br>&lt;/b>&lt;b>&lt;i>dependent_continuant&lt;/i>&lt;/b>&lt;i>&lt;div style=&quot;margin-left:5px;margin-top:2px;margin-bottom:2px&quot;>Definition: A continuant [snap:Continuant] that is either dependent on one or other independent continuant [snap:IndependentContinuant] bearers or inheres in or is borne by other entities.&lt;/div>&lt;/i>&lt;b>super:  continuant&lt;br>&lt;/b>&lt;font color=&quot;#000080&quot;>(&lt;i>and&lt;/i>&amp;nbsp;(&lt;i>not&lt;/i>&amp;nbsp;independent_continuant)&amp;nbsp;continuant&lt;br>&amp;nbsp;(&lt;i>or&lt;/i>&amp;nbsp;generically_dependent_continuant&amp;nbsp;specifically_dependent_continuant))&lt;br>&lt;/font>&lt;/div>&lt;/html>"/>
<branch><attribute name="name" value="specifically_dependent_continuant(2)"/><attribute name="entity" value="http://www.ifomis.org/bfo/1.1/snap#SpecificallyDependentContinuant"/><attribute name="tooltip" value="&lt;html>&lt;div style=&quot;font-size:11;width:500&quot;>&lt;b>Class: http://www.ifomis.org/bfo/1.1/snap#SpecificallyDependentContinuant&lt;br>&lt;/b>&lt;b>&lt;i>specifically_dependent_continuant&lt;/i>&lt;/b>&lt;i>&lt;div style=&quot;margin-left:5px;margin-top:2px;margin-bottom:2px&quot;>Synonyms: property, trope, mode; Examples: the mass of a cloud, the smell of mozzarella, the liquidity of blood, the color of a tomato, the disposition of fish to decay, the role of being a doctor, the function of the heart in the body: to pump blood, to receive de-oxygenated and oxygenated blood, etc.; Definition: A continuant [snap:Continuant] that inheres in or is borne by other entities. Every instance of A requires some specific instance of B which must always be the same.&lt;/div>&lt;/i>&lt;b>super:  dependent_continuant&lt;br>&lt;/b>&lt;font color=&quot;#000080&quot;>(equivalent-class&amp;nbsp;specifically_dependent_continuant&amp;nbsp;(&lt;i>or&lt;/i>&amp;nbsp;quality&amp;nbsp;realizable_entity))&lt;br>&lt;/font>&lt;/div>&lt;/html>"/>
<branch><attribute name="name" value="realizable_entity(3)"/><attribute name="entity" value="http://www.ifomis.org/bfo/1.1/snap#RealizableEntity"/><attribute name="tooltip" value="&lt;html>&lt;div style=&quot;font-size:11;width:500&quot;>&lt;b>Class: http://www.ifomis.org/bfo/1.1/snap#RealizableEntity&lt;br>&lt;/b>&lt;b>&lt;i>realizable_entity&lt;/i>&lt;/b>&lt;i>&lt;div style=&quot;margin-left:5px;margin-top:2px;margin-bottom:2px&quot;>Comment: If a realizable entity [snap:RealizableEntity] inheres in a continuant [snap:Continuant], this does not imply that it is actually realized.; Examples: the role of being a doctor, the function of the reproductive organs, the disposition of blood to coagulate, the disposition of metal to conduct electricity; Definition: A specifically dependent continuant [snap:SpecificallyDependentContinuant] that inheres in continuant [snap:Continuant] entities and are not exhibited in full at every time in which it inheres in an entity or group of entities. The exhibition or actualization of a realizable entity is a particular manifestation, functioning or process that occurs under certain circumstances.&lt;/div>&lt;/i>&lt;b>super:  specifically_dependent_continuant&lt;br>&lt;/b>&lt;font color=&quot;#000080&quot;>(&lt;i>and&lt;/i>&amp;nbsp;specifically_dependent_continuant&amp;nbsp;dependent_continuant)&lt;br>&lt;/font>&lt;/div>&lt;/html>"/>
<leaf><attribute name="name" value="function"/><attribute name="entity" value="http://www.ifomis.org/bfo/1.1/snap#Function"/><attribute name="tooltip" value="&lt;html>&lt;div style=&quot;font-size:11;width:500&quot;>&lt;b>Class: http://www.ifomis.org/bfo/1.1/snap#Function&lt;br>&lt;/b>&lt;b>&lt;i>function&lt;/i>&lt;/b>&lt;i>&lt;div style=&quot;margin-left:5px;margin-top:2px;margin-bottom:2px&quot;>Examples: the function of a birth canal to enable transport, the function of the heart in the body: to pump blood, to receive de-oxygenated and oxygenated blood, etc., the function of reproduction in the transmission of genetic material, the digestive function of the stomach to nutriate the body, the function of a hammer to drive in nails, the function of a computer program to compute mathematical equations, the function of an automobile to provide transportation, the function of a judge in a court of law; Definition: A realizable entity [snap:RealizableEntity] the manifestation of which is an essentially end-directed activity of a continuant [snap:Continuant] entity in virtue of that continuant [snap:Continuant] entity being a specific kind of entity in the kind or kinds of contexts that it is made for.&lt;/div>&lt;/i>&lt;b>super:  realizable_entity&lt;br>&lt;/b>&lt;font color=&quot;#000080&quot;>(&lt;i>and&lt;/i>&amp;nbsp;(&lt;i>not&lt;/i>&amp;nbsp;disposition)&amp;nbsp;realizable_entity)&lt;br>&lt;/font>&lt;/div>&lt;/html>"/></leaf>
<leaf><attribute name="name" value="role"/><attribute name="entity" value="http://www.ifomis.org/bfo/1.1/snap#Role"/><attribute name="tooltip" value="&lt;html>&lt;div style=&quot;font-size:11;width:500&quot;>&lt;b>Class: http://www.ifomis.org/bfo/1.1/snap#Role&lt;br>&lt;/b>&lt;b>&lt;i>role&lt;/i>&lt;/b>&lt;i>&lt;div style=&quot;margin-left:5px;margin-top:2px;margin-bottom:2px&quot;>Examples: the role of a person as a surgeon, the role of a chemical compound in an experiment, the role of a patient relative as defined by a hospital administrative form, the role of a woman as a legal mother in the context of system of laws, the role of a biological grandfather as legal guardian in the context of a system of laws, the role of ingested matter in digestion, the role of a student in a university; Definition: A realizable entity [snap:RealizableEntity] the manifestation of which brings about some result or end that is not essential to a continuant [snap:Continuant] in virtue of the kind of thing that it is but that can be served or participated in by that kind of continuant [snap:Continuant] in some kinds of natural, social or institutional contexts.&lt;/div>&lt;/i>&lt;b>super:  realizable_entity&lt;br>&lt;/b>&lt;font color=&quot;#000080&quot;>(&lt;i>and&lt;/i>&amp;nbsp;realizable_entity&amp;nbsp;(&lt;i>disjoint-with&lt;/i>&amp;nbsp;function&amp;nbsp;disposition))&lt;br>&lt;/font>&lt;/div>&lt;/html>"/></leaf>
<branch><attribute name="name" value="disposition(3)"/><attribute name="entity" value="http://www.ifomis.org/bfo/1.1/snap#Disposition"/><attribute name="tooltip" value="&lt;html>&lt;div style=&quot;font-size:11;width:500&quot;>&lt;b>Class: http://www.ifomis.org/bfo/1.1/snap#Disposition&lt;br>&lt;/b>&lt;b>&lt;i>disposition&lt;/i>&lt;/b>&lt;i>&lt;div style=&quot;margin-left:5px;margin-top:2px;margin-bottom:2px&quot;>Examples: the disposition of vegetables to decay when not refrigerated, the disposition of a vase to brake if dropped, the disposition of blood to coagulate, the disposition of a patient with a weakened immune system to contract disease, the disposition of metal to conduct electricity.; Definition: A realizable entity [snap:RealizableEntity] that essentially causes a specific process or transformation in the object [snap:Object] in which it inheres, under specific circumstances and in conjunction with the laws of nature. A general formula for dispositions is: X (object [snap:Object] has the disposition D to (transform, initiate a process) R under conditions C.&lt;/div>&lt;/i>&lt;b>super:  realizable_entity&lt;br>&lt;/b>&lt;font color=&quot;#000080&quot;>(&lt;i>and&lt;/i>&amp;nbsp;realizable_entity&amp;nbsp;(&lt;i>disjoint-with&lt;/i>&amp;nbsp;role&amp;nbsp;function))&lt;br>&lt;/font>&lt;/div>&lt;/html>"/>
<branch><attribute name="name" value="disease(2)"/><attribute name="entity" value="http://purl.obolibrary.org/obo/OGMS_0000031"/><attribute name="tooltip" value="&lt;html>&lt;div style=&quot;font-size:11;width:500&quot;>&lt;b>Class: http://purl.obolibrary.org/obo/OGMS_0000031&lt;br>&lt;/b>&lt;b>&lt;i>disease&lt;/i>&lt;/b>&lt;i>&lt;div style=&quot;margin-left:5px;margin-top:2px;margin-bottom:2px&quot;>A disposition (i) to undergo pathological processes that (ii) exists in an organism because of one or more disorders in that organism.&lt;/div>&lt;/i>&lt;b>super:  disposition&lt;br>&lt;/b>&lt;font color=&quot;#000080&quot;>&lt;/font>&lt;hr>&lt;i>curator note&lt;/i>: creation date: 2009-06-23T11:21:20Z&lt;br>&lt;i>definition source&lt;/i>: http://ontology.buffalo.edu/medo/Disease_and_Diagnosis.pdf&lt;br>&lt;i>definition editor&lt;/i>: Albert Goldfain&lt;br>&lt;i>definition&lt;/i>: A disposition (i) to undergo pathological processes that (ii) exists in an organism because of one or more disorders in that organism.&lt;br>&lt;/div>&lt;/html>"/>
<leaf><attribute name="name" value="constitutional genetic disease"/><attribute name="entity" value="http://purl.obolibrary.org/obo/OGMS_0000035"/><attribute name="tooltip" value="&lt;html>&lt;div style=&quot;font-size:11;width:500&quot;>&lt;b>Class: http://purl.obolibrary.org/obo/OGMS_0000035&lt;br>&lt;/b>&lt;b>&lt;i>constitutional genetic disease&lt;/i>&lt;/b>&lt;i>&lt;div style=&quot;margin-left:5px;margin-top:2px;margin-bottom:2px&quot;>A disease whose physical basis is a constitutional genetic disorder.&lt;/div>&lt;/i>&lt;b>super:  disease&lt;br>&lt;/b>&lt;font color=&quot;#000080&quot;>&lt;/font>&lt;hr>&lt;i>curator note&lt;/i>: creation date: 2009-06-23T11:24:59Z&lt;br>&lt;i>definition source&lt;/i>: http://ontology.buffalo.edu/medo/Disease_and_Diagnosis.pdf&lt;br>&lt;i>definition editor&lt;/i>: Albert Goldfain&lt;br>&lt;i>definition&lt;/i>: A disease whose physical basis is a constitutional genetic disorder.&lt;br>&lt;/div>&lt;/html>"/></leaf>
<leaf><attribute name="name" value="acquired genetic disease"/><attribute name="entity" value="http://purl.obolibrary.org/obo/OGMS_0000034"/><attribute name="tooltip" value="&lt;html>&lt;div style=&quot;font-size:11;width:500&quot;>&lt;b>Class: http://purl.obolibrary.org/obo/OGMS_0000034&lt;br>&lt;/b>&lt;b>&lt;i>acquired genetic disease&lt;/i>&lt;/b>&lt;i>&lt;div style=&quot;margin-left:5px;margin-top:2px;margin-bottom:2px&quot;>A disease whose physical basis is an acquired genetic disorder.&lt;/div>&lt;/i>&lt;b>super:  disease&lt;br>&lt;/b>&lt;font color=&quot;#000080&quot;>&lt;/font>&lt;hr>&lt;i>curator note&lt;/i>: creation date: 2009-06-23T11:24:05Z&lt;br>&lt;i>definition source&lt;/i>: http://ontology.buffalo.edu/medo/Disease_and_Diagnosis.pdf&lt;br>&lt;i>definition editor&lt;/i>: Albert Goldfain&lt;br>&lt;i>definition&lt;/i>: A disease whose physical basis is an acquired genetic disorder.&lt;br>&lt;/div>&lt;/html>"/></leaf>
</branch>
<branch><attribute name="name" value="homeostasis(2)"/><attribute name="entity" value="http://purl.obolibrary.org/obo/OGMS_0000032"/><attribute name="tooltip" value="&lt;html>&lt;div style=&quot;font-size:11;width:500&quot;>&lt;b>Class: http://purl.obolibrary.org/obo/OGMS_0000032&lt;br>&lt;/b>&lt;b>&lt;i>homeostasis&lt;/i>&lt;/b>&lt;i>&lt;br>&lt;/i>&lt;b>super:  disposition&lt;br>&lt;/b>&lt;font color=&quot;#000080&quot;>&lt;/font>&lt;hr>&lt;i>curator note&lt;/i>: creation date: 2009-06-23T11:22:01Z&lt;br>&lt;i>definition editor&lt;/i>: Albert Goldfain&lt;br>&lt;/div>&lt;/html>"/>
<leaf><attribute name="name" value="normal homeostasis"/><attribute name="entity" value="http://purl.obolibrary.org/obo/OGMS_0000038"/><attribute name="tooltip" value="&lt;html>&lt;div style=&quot;font-size:11;width:500&quot;>&lt;b>Class: http://purl.obolibrary.org/obo/OGMS_0000038&lt;br>&lt;/b>&lt;b>&lt;i>normal homeostasis&lt;/i>&lt;/b>&lt;i>&lt;div style=&quot;margin-left:5px;margin-top:2px;margin-bottom:2px&quot;>Homeostasis of a type that is not clinically abnormal.&lt;/div>&lt;/i>&lt;b>super:  homeostasis&lt;br>&lt;/b>&lt;font color=&quot;#000080&quot;>&lt;/font>&lt;hr>&lt;i>curator note&lt;/i>: creation date: 2009-06-23T11:27:28Z&lt;br>&lt;i>definition source&lt;/i>: http://ontology.buffalo.edu/medo/Disease_and_Diagnosis.pdf&lt;br>&lt;i>definition editor&lt;/i>: Albert Goldfain&lt;br>&lt;i>definition&lt;/i>: Homeostasis of a type that is not clinically abnormal.&lt;br>&lt;/div>&lt;/html>"/></leaf>
<leaf><attribute name="name" value="abnormal homeostasis"/><attribute name="entity" value="http://purl.obolibrary.org/obo/OGMS_0000037"/><attribute name="tooltip" value="&lt;html>&lt;div style=&quot;font-size:11;width:500&quot;>&lt;b>Class: http://purl.obolibrary.org/obo/OGMS_0000037&lt;br>&lt;/b>&lt;b>&lt;i>abnormal homeostasis&lt;/i>&lt;/b>&lt;i>&lt;div style=&quot;margin-left:5px;margin-top:2px;margin-bottom:2px&quot;>Homeostasis that is clinically abnormal for an organism of a given type and age in a given environment.&lt;/div>&lt;/i>&lt;b>super:  homeostasis&lt;br>&lt;/b>&lt;font color=&quot;#000080&quot;>&lt;/font>&lt;hr>&lt;i>curator note&lt;/i>: creation date: 2009-06-23T11:26:44Z&lt;br>&lt;i>definition source&lt;/i>: http://ontology.buffalo.edu/medo/Disease_and_Diagnosis.pdf&lt;br>&lt;i>definition editor&lt;/i>: Albert Goldfain&lt;br>&lt;i>definition&lt;/i>: Homeostasis that is clinically abnormal for an organism of a given type and age in a given environment.&lt;br>&lt;/div>&lt;/html>"/></leaf>
</branch>
<branch><attribute name="name" value="predisposition to disease of type X(1)"/><attribute name="entity" value="http://purl.obolibrary.org/obo/OGMS_0000030"/><attribute name="tooltip" value="&lt;html>&lt;div style=&quot;font-size:11;width:500&quot;>&lt;b>Class: http://purl.obolibrary.org/obo/OGMS_0000030&lt;br>&lt;/b>&lt;b>&lt;i>predisposition to disease of type X&lt;/i>&lt;/b>&lt;i>&lt;div style=&quot;margin-left:5px;margin-top:2px;margin-bottom:2px&quot;>A disposition in an organism that constitutes an increased risk of the organism's subsequently developing the disease X.&lt;/div>&lt;/i>&lt;b>super:  disposition&lt;br>&lt;/b>&lt;font color=&quot;#000080&quot;>&lt;/font>&lt;hr>&lt;i>curator note&lt;/i>: creation date: 2009-06-23T11:20:25Z&lt;br>&lt;i>definition source&lt;/i>: http://ontology.buffalo.edu/medo/Disease_and_Diagnosis.pdf&lt;br>&lt;i>definition editor&lt;/i>: Albert Goldfain&lt;br>&lt;i>definition&lt;/i>: A disposition in an organism that constitutes an increased risk of the organism's subsequently developing the disease X.&lt;br>&lt;/div>&lt;/html>"/>
<leaf><attribute name="name" value="genetic predisposition to disease of type X"/><attribute name="entity" value="http://purl.obolibrary.org/obo/OGMS_0000033"/><attribute name="tooltip" value="&lt;html>&lt;div style=&quot;font-size:11;width:500&quot;>&lt;b>Class: http://purl.obolibrary.org/obo/OGMS_0000033&lt;br>&lt;/b>&lt;b>&lt;i>genetic predisposition to disease of type X&lt;/i>&lt;/b>&lt;i>&lt;div style=&quot;margin-left:5px;margin-top:2px;margin-bottom:2px&quot;>A predisposition to disease of type X whose physical basis is a constitutional abnormality in an organism's genome. This abnormality is the physical basis for the increased risk of acquiring the disease X.&lt;/div>&lt;/i>&lt;b>super:  predisposition to disease of type X&lt;br>&lt;/b>&lt;font color=&quot;#000080&quot;>&lt;/font>&lt;hr>&lt;i>curator note&lt;/i>: creation date: 2009-06-23T11:23:07Z&lt;br>&lt;i>definition source&lt;/i>: http://ontology.buffalo.edu/medo/Disease_and_Diagnosis.pdf&lt;br>&lt;i>definition editor&lt;/i>: Albert Goldfain&lt;br>&lt;i>definition&lt;/i>: A predisposition to disease of type X whose physical basis is a constitutional abnormality in an organism's genome. This abnormality is the physical basis for the increased risk of acquiring the disease X.&lt;br>&lt;/div>&lt;/html>"/></leaf>
</branch>
</branch>
</branch>
<branch><attribute name="name" value="quality(1)"/><attribute name="entity" value="http://www.ifomis.org/bfo/1.1/snap#Quality"/><attribute name="tooltip" value="&lt;html>&lt;div style=&quot;font-size:11;width:500&quot;>&lt;b>Class: http://www.ifomis.org/bfo/1.1/snap#Quality&lt;br>&lt;/b>&lt;b>&lt;i>quality&lt;/i>&lt;/b>&lt;i>&lt;div style=&quot;margin-left:5px;margin-top:2px;margin-bottom:2px&quot;>Examples: the color of a tomato, the ambient temperature of air, the circumference of a waist, the shape of a nose, the mass of a piece of gold, the weight of a chimpanzee; Definition: A specifically dependent continuant [snap:SpecificallyDependentContinuant] that is exhibited if it inheres in an entity or entities at all (a categorical property).&lt;/div>&lt;/i>&lt;b>super:  specifically_dependent_continuant&lt;br>&lt;/b>&lt;font color=&quot;#000080&quot;>(&lt;i>and&lt;/i>&amp;nbsp;(&lt;i>not&lt;/i>&amp;nbsp;realizable_entity)&amp;nbsp;dependent_continuant&lt;br>&amp;nbsp;specifically_dependent_continuant)&lt;br>&lt;/font>&lt;/div>&lt;/html>"/>
<branch><attribute name="name" value="configuration(1)"/><attribute name="entity" value="http://purl.obolibrary.org/obo/OGMS_0000039"/><attribute name="tooltip" value="&lt;html>&lt;div style=&quot;font-size:11;width:500&quot;>&lt;b>Class: http://purl.obolibrary.org/obo/OGMS_0000039&lt;br>&lt;/b>&lt;b>&lt;i>configuration&lt;/i>&lt;/b>&lt;i>&lt;div style=&quot;margin-left:5px;margin-top:2px;margin-bottom:2px&quot;>A quality which is an spatial arrangement or distribution of a(n) independent continuant(s) across a Three Dimensional Region.&lt;/div>&lt;/i>&lt;b>super:  quality&lt;br>&lt;/b>&lt;font color=&quot;#000080&quot;>&lt;/font>&lt;hr>&lt;i>curator note&lt;/i>: creation date: 2009-06-23T11:36:24Z&lt;br>&lt;i>definition source&lt;/i>: http://ontology.buffalo.edu/medo/Disease_and_Diagnosis.pdf&lt;br>&lt;i>definition editor&lt;/i>: Albert Goldfain&lt;br>&lt;i>definition&lt;/i>: A quality which is an spatial arrangement or distribution of a(n) independent continuant(s) across a Three Dimensional Region.&lt;br>&lt;/div>&lt;/html>"/>
<leaf><attribute name="name" value="pathological physical configuration"/><attribute name="entity" value="http://purl.obolibrary.org/obo/OGMS_0000040"/><attribute name="tooltip" value="&lt;html>&lt;div style=&quot;font-size:11;width:500&quot;>&lt;b>Class: http://purl.obolibrary.org/obo/OGMS_0000040&lt;br>&lt;/b>&lt;b>&lt;i>pathological physical configuration&lt;/i>&lt;/b>&lt;i>&lt;div style=&quot;margin-left:5px;margin-top:2px;margin-bottom:2px&quot;>A configuration which deviates in some way from a canonical configuration for a particular organism.&lt;/div>&lt;/i>&lt;b>super:  configuration&lt;br>&lt;/b>&lt;font color=&quot;#000080&quot;>&lt;/font>&lt;hr>&lt;i>curator note&lt;/i>: creation date: 2009-06-23T11:36:58Z&lt;br>&lt;i>definition source&lt;/i>: http://ontology.buffalo.edu/medo/Disease_and_Diagnosis.pdf&lt;br>&lt;i>definition editor&lt;/i>: Albert Goldfain&lt;br>&lt;i>definition&lt;/i>: A configuration which deviates in some way from a canonical configuration for a particular organism.&lt;br>&lt;/div>&lt;/html>"/></leaf>
</branch>
</branch>
</branch>
<branch><attribute name="name" value="generically_dependent_continuant(2)"/><attribute name="entity" value="http://www.ifomis.org/bfo/1.1/snap#GenericallyDependentContinuant"/><attribute name="tooltip" value="&lt;html>&lt;div style=&quot;font-size:11;width:500&quot;>&lt;b>Class: http://www.ifomis.org/bfo/1.1/snap#GenericallyDependentContinuant&lt;br>&lt;/b>&lt;b>&lt;i>generically_dependent_continuant&lt;/i>&lt;/b>&lt;i>&lt;div style=&quot;margin-left:5px;margin-top:2px;margin-bottom:2px&quot;>Examples: a certain PDF file that exists in different and in several hard drives; Definition: A continuant [snap:Continuant] that is dependent on one or other independent continuant [snap:IndependentContinuant] bearers. For every instance of A requires some instance of (an independent continuant [snap:IndependentContinuant] type) B but which instance of B serves can change from time to time.&lt;/div>&lt;/i>&lt;b>super:  dependent_continuant&lt;br>&lt;/b>&lt;font color=&quot;#000080&quot;>(&lt;i>and&lt;/i>&amp;nbsp;(&lt;i>not&lt;/i>&amp;nbsp;specifically_dependent_continuant)&amp;nbsp;dependent_continuant)&lt;br>&lt;/font>&lt;/div>&lt;/html>"/>
<branch><attribute name="name" value="information content entity(1)"/><attribute name="entity" value="http://purl.obolibrary.org/obo/IAO_0000030"/><attribute name="tooltip" value="&lt;html>&lt;div style=&quot;font-size:11;width:500&quot;>&lt;b>Class: http://purl.obolibrary.org/obo/IAO_0000030&lt;br>&lt;/b>&lt;b>&lt;i>information content entity&lt;/i>&lt;/b>&lt;i>&lt;div style=&quot;margin-left:5px;margin-top:2px;margin-bottom:2px&quot;>an information content entity is an entity that is generically dependent on some artifact and stands in relation of aboutness to some entity&lt;/div>&lt;/i>&lt;b>super:  &lt;font color=&quot;red&quot;>generically_dependent_continuant&lt;/font>&lt;br>&lt;/b>&lt;font color=&quot;#000080&quot;>&lt;/font>&lt;hr>&lt;i>definition source&lt;/i>: OBO:sourced 'OBI:0000142'&lt;br>&lt;i>definition&lt;/i>: an information content entity is an entity that is generically dependent on some artifact and stands in relation of aboutness to some entity&lt;br>&lt;/div>&lt;/html>"/>
<branch><attribute name="name" value="data item(5)"/><attribute name="entity" value="http://purl.obolibrary.org/obo/IAO_0000027"/><attribute name="tooltip" value="&lt;html>&lt;div style=&quot;font-size:11;width:500&quot;>&lt;b>Class: http://purl.obolibrary.org/obo/IAO_0000027&lt;br>&lt;/b>&lt;b>&lt;i>data item&lt;/i>&lt;/b>&lt;i>&lt;div style=&quot;margin-left:5px;margin-top:2px;margin-bottom:2px&quot;>a data item is an information content entity that is intended to be a truthful statement about something (modulo, e.g., measurement precision or other systematic errors) and is constructed/acquired by a method which reliably tends to produce (approximately) truthful statements.&lt;/div>&lt;/i>&lt;b>super:  &lt;font color=&quot;red&quot;>information content entity&lt;/font>&lt;br>&lt;/b>&lt;font color=&quot;#000080&quot;>&lt;/font>&lt;hr>&lt;i>definition source&lt;/i>: OBO:imported 'http://purl.obolibrary.org/obo/iao.owl'&lt;br>&lt;i>definition&lt;/i>: a data item is an information content entity that is intended to be a truthful statement about something (modulo, e.g., measurement precision or other systematic errors) and is constructed/acquired by a method which reliably tends to produce (approximately) truthful statements.&lt;br>&lt;/div>&lt;/html>"/>
<leaf><attribute name="name" value="diagnosis"/><attribute name="entity" value="http://purl.obolibrary.org/obo/OGMS_0000073"/><attribute name="tooltip" value="&lt;html>&lt;div style=&quot;font-size:11;width:500&quot;>&lt;b>Class: http://purl.obolibrary.org/obo/OGMS_0000073&lt;br>&lt;/b>&lt;b>&lt;i>diagnosis&lt;/i>&lt;/b>&lt;i>&lt;div style=&quot;margin-left:5px;margin-top:2px;margin-bottom:2px&quot;>The representation of a conclusion of an interpretive process that has as input a clinical picture of a given patient and as output an assertion (diagnostic statement) to the effect that the patient has a disease of such and such a type.&lt;/div>&lt;/i>&lt;b>super:  data item&lt;br>&lt;/b>&lt;font color=&quot;#000080&quot;>&lt;/font>&lt;hr>&lt;i>curator note&lt;/i>: creation date: 2009-06-23T12:42:23Z&lt;br>&lt;i>definition source&lt;/i>: http://ontology.buffalo.edu/medo/Disease_and_Diagnosis.pdf&lt;br>&lt;i>definition editor&lt;/i>: Albert Goldfain&lt;br>&lt;i>definition&lt;/i>: The representation of a conclusion of an interpretive process that has as input a clinical picture of a given patient and as output an assertion (diagnostic statement) to the effect that the patient has a disease of such and such a type.&lt;br>&lt;/div>&lt;/html>"/></leaf>
<branch><attribute name="name" value="clinical finding(4)"/><attribute name="entity" value="http://purl.obolibrary.org/obo/OGMS_0000014"/><attribute name="tooltip" value="&lt;html>&lt;div style=&quot;font-size:11;width:500&quot;>&lt;b>Class: http://purl.obolibrary.org/obo/OGMS_0000014&lt;br>&lt;/b>&lt;b>&lt;i>clinical finding&lt;/i>&lt;/b>&lt;i>&lt;div style=&quot;margin-left:5px;margin-top:2px;margin-bottom:2px&quot;>A representation of a bodily feature of a patient that is either the output of a clinical history taking or a physical examination or an image finding, or some combination thereof.&lt;/div>&lt;/i>&lt;b>super:  data item&lt;br>&lt;/b>&lt;font color=&quot;#000080&quot;>&lt;/font>&lt;hr>&lt;i>curator note&lt;/i>: creation date: 2009-06-23T10:18:02Z&lt;br>&lt;i>definition source&lt;/i>: http://ontology.buffalo.edu/medo/Disease_and_Diagnosis.pdf&lt;br>&lt;i>definition editor&lt;/i>: Albert Goldfain&lt;br>&lt;i>definition&lt;/i>: A representation of a bodily feature of a patient that is either the output of a clinical history taking or a physical examination or an image finding, or some combination thereof.&lt;br>&lt;/div>&lt;/html>"/>
<leaf><attribute name="name" value="image finding"/><attribute name="entity" value="http://purl.obolibrary.org/obo/OGMS_0000017"/><attribute name="tooltip" value="&lt;html>&lt;div style=&quot;font-size:11;width:500&quot;>&lt;b>Class: http://purl.obolibrary.org/obo/OGMS_0000017&lt;br>&lt;/b>&lt;b>&lt;i>image finding&lt;/i>&lt;/b>&lt;i>&lt;div style=&quot;margin-left:5px;margin-top:2px;margin-bottom:2px&quot;>A representation of an image that supports an inference to an assertion about some quality of a patient.&lt;/div>&lt;/i>&lt;b>super:  clinical finding&lt;br>&lt;/b>&lt;font color=&quot;#000080&quot;>&lt;/font>&lt;hr>&lt;i>curator note&lt;/i>: creation date: 2009-06-23T10:21:10Z&lt;br>&lt;i>definition source&lt;/i>: http://ontology.buffalo.edu/medo/Disease_and_Diagnosis.pdf&lt;br>&lt;i>definition editor&lt;/i>: Albert Goldfain&lt;br>&lt;i>definition&lt;/i>: A representation of an image that supports an inference to an assertion about some quality of a patient.&lt;br>&lt;/div>&lt;/html>"/></leaf>
<leaf><attribute name="name" value="clinical history"/><attribute name="entity" value="http://purl.obolibrary.org/obo/OGMS_0000015"/><attribute name="tooltip" value="&lt;html>&lt;div style=&quot;font-size:11;width:500&quot;>&lt;b>Class: http://purl.obolibrary.org/obo/OGMS_0000015&lt;br>&lt;/b>&lt;b>&lt;i>clinical history&lt;/i>&lt;/b>&lt;i>&lt;div style=&quot;margin-left:5px;margin-top:2px;margin-bottom:2px&quot;>A series of statements representing health-relevant features of a patient and of a patient's family.&lt;/div>&lt;/i>&lt;b>super:  clinical finding&lt;br>&lt;/b>&lt;font color=&quot;#000080&quot;>&lt;/font>&lt;hr>&lt;i>curator note&lt;/i>: creation date: 2009-06-23T10:18:59Z&lt;br>&lt;i>definition source&lt;/i>: http://ontology.buffalo.edu/medo/Disease_and_Diagnosis.pdf&lt;br>&lt;i>definition editor&lt;/i>: Albert Goldfain&lt;br>&lt;i>definition&lt;/i>: A series of statements representing health-relevant features of a patient and of a patient's family.&lt;br>&lt;/div>&lt;/html>"/></leaf>
<leaf><attribute name="name" value="physical examination finding"/><attribute name="entity" value="http://purl.obolibrary.org/obo/OGMS_0000083"/><attribute name="tooltip" value="&lt;html>&lt;div style=&quot;font-size:11;width:500&quot;>&lt;b>Class: http://purl.obolibrary.org/obo/OGMS_0000083&lt;br>&lt;/b>&lt;b>&lt;i>physical examination finding&lt;/i>&lt;/b>&lt;i>&lt;div style=&quot;margin-left:5px;margin-top:2px;margin-bottom:2px&quot;>TODO: Define.&lt;/div>&lt;/i>&lt;b>super:  clinical finding&lt;br>&lt;/b>&lt;font color=&quot;#000080&quot;>&lt;/font>&lt;hr>&lt;i>curator note&lt;/i>: creation date: 2009-11-24T04:51:11Z&lt;br>&lt;i>definition source&lt;/i>: http://code.google.com/p/ogms/issues/detail?id=26&lt;br>&lt;i>definition editor&lt;/i>: Albert Goldfain&lt;br>&lt;i>definition&lt;/i>: TODO: Define.&lt;br>&lt;/div>&lt;/html>"/></leaf>
<leaf><attribute name="name" value="laboratory finding"/><attribute name="entity" value="http://purl.obolibrary.org/obo/OGMS_0000018"/><attribute name="tooltip" value="&lt;html>&lt;div style=&quot;font-size:11;width:500&quot;>&lt;b>Class: http://purl.obolibrary.org/obo/OGMS_0000018&lt;br>&lt;/b>&lt;b>&lt;i>laboratory finding&lt;/i>&lt;/b>&lt;i>&lt;div style=&quot;margin-left:5px;margin-top:2px;margin-bottom:2px&quot;>A representation of a quality of a specimen that is the output of a laboratory test and that can support an inference to an assertion about some quality of the patient.&lt;/div>&lt;/i>&lt;b>super:  clinical finding&lt;br>&lt;/b>&lt;font color=&quot;#000080&quot;>&lt;/font>&lt;hr>&lt;i>curator note&lt;/i>: creation date: 2009-06-23T10:21:58Z&lt;br>&lt;i>definition source&lt;/i>: http://ontology.buffalo.edu/medo/Disease_and_Diagnosis.pdf&lt;br>&lt;i>definition editor&lt;/i>: Albert Goldfain&lt;br>&lt;i>definition&lt;/i>: A representation of a quality of a specimen that is the output of a laboratory test and that can support an inference to an assertion about some quality of the patient.&lt;br>&lt;/div>&lt;/html>"/></leaf>
</branch>
<branch><attribute name="name" value="clinical picture(1)"/><attribute name="entity" value="http://purl.obolibrary.org/obo/OGMS_0000016"/><attribute name="tooltip" value="&lt;html>&lt;div style=&quot;font-size:11;width:500&quot;>&lt;b>Class: http://purl.obolibrary.org/obo/OGMS_0000016&lt;br>&lt;/b>&lt;b>&lt;i>clinical picture&lt;/i>&lt;/b>&lt;i>&lt;div style=&quot;margin-left:5px;margin-top:2px;margin-bottom:2px&quot;>A representation of the clinically significant bodily features of a patient that is inferred from the totality of clinical findings about the given patient.&lt;/div>&lt;/i>&lt;b>super:  data item&lt;br>&lt;/b>&lt;font color=&quot;#000080&quot;>&lt;/font>&lt;hr>&lt;i>curator note&lt;/i>: creation date: 2009-06-23T10:20:20Z&lt;br>&lt;i>definition source&lt;/i>: http://ontology.buffalo.edu/medo/Disease_and_Diagnosis.pdf&lt;br>&lt;i>definition editor&lt;/i>: Albert Goldfain&lt;br>&lt;i>definition&lt;/i>: A representation of the clinically significant bodily features of a patient that is inferred from the totality of clinical findings about the given patient.&lt;br>&lt;/div>&lt;/html>"/>
<leaf><attribute name="name" value="syndrome"/><attribute name="entity" value="http://purl.obolibrary.org/obo/OGMS_0000086"/><attribute name="tooltip" value="&lt;html>&lt;div style=&quot;font-size:11;width:500&quot;>&lt;b>Class: http://purl.obolibrary.org/obo/OGMS_0000086&lt;br>&lt;/b>&lt;b>&lt;i>syndrome&lt;/i>&lt;/b>&lt;i>&lt;div style=&quot;margin-left:5px;margin-top:2px;margin-bottom:2px&quot;>A clinical picture that is an association of symptoms, signs and other clinical findings that collectively indicate or characterize a disease or disorder.&lt;/div>&lt;/i>&lt;b>super:  clinical picture&lt;br>&lt;/b>&lt;font color=&quot;#000080&quot;>&lt;/font>&lt;hr>&lt;i>curator note&lt;/i>: creation date: 2009-11-24T04:51:11Z&lt;br>&lt;i>definition source&lt;/i>: http://code.google.com/p/ogms/issues/detail?id=32&lt;br>&lt;i>definition editor&lt;/i>: Albert Goldfain&lt;br>&lt;i>definition&lt;/i>: A clinical picture that is an association of symptoms, signs and other clinical findings that collectively indicate or characterize a disease or disorder.&lt;br>&lt;/div>&lt;/html>"/></leaf>
</branch>
<branch><attribute name="name" value="data about an ontology part(8)"/><attribute name="entity" value="http://purl.obolibrary.org/obo/IAO_0000102"/><attribute name="tooltip" value="&lt;html>&lt;div style=&quot;font-size:11;width:500&quot;>&lt;b>Class: http://purl.obolibrary.org/obo/IAO_0000102&lt;br>&lt;/b>&lt;b>&lt;i>data about an ontology part&lt;/i>&lt;/b>&lt;i>&lt;div style=&quot;margin-left:5px;margin-top:2px;margin-bottom:2px&quot;>data about an ontology part is a data item about a part of an ontology, for example a term&lt;/div>&lt;/i>&lt;b>super:  data item&lt;br>&lt;/b>&lt;font color=&quot;#000080&quot;>&lt;/font>&lt;hr>&lt;i>definition editor&lt;/i>: Person:Alan Ruttenberg&lt;br>&lt;i>definition&lt;/i>: data about an ontology part is a data item about a part of an ontology, for example a term&lt;br>&lt;/div>&lt;/html>"/>
<leaf><attribute name="name" value="Subset"/><attribute name="entity" value="http://www.geneontology.org/formats/oboInOwl#Subset"/><attribute name="tooltip" value="&lt;html>&lt;div style=&quot;font-size:11;width:500&quot;>&lt;b>Class: http://www.geneontology.org/formats/oboInOwl#Subset&lt;br>&lt;/b>&lt;i>&lt;/i>&lt;b>super:  data about an ontology part&lt;br>&lt;/b>&lt;font color=&quot;#000080&quot;>(equivalent-class&amp;nbsp;Subset&amp;nbsp;(&lt;i>has&lt;/i>&amp;nbsp;core))&lt;br>&lt;/font>&lt;/div>&lt;/html>"/></leaf>
<leaf><attribute name="name" value="SynonymType"/><attribute name="entity" value="http://www.geneontology.org/formats/oboInOwl#SynonymType"/><attribute name="tooltip" value="&lt;html>&lt;div style=&quot;font-size:11;width:500&quot;>&lt;b>Class: http://www.geneontology.org/formats/oboInOwl#SynonymType&lt;br>&lt;/b>&lt;i>&lt;/i>&lt;b>super:  data about an ontology part&lt;br>&lt;/b>&lt;font color=&quot;#000080&quot;>&lt;/font>&lt;/div>&lt;/html>"/></leaf>
<leaf><attribute name="name" value="Definition"/><attribute name="entity" value="http://www.geneontology.org/formats/oboInOwl#Definition"/><attribute name="tooltip" value="&lt;html>&lt;div style=&quot;font-size:11;width:500&quot;>&lt;b>Class: http://www.geneontology.org/formats/oboInOwl#Definition&lt;br>&lt;/b>&lt;i>&lt;/i>&lt;b>super:  data about an ontology part&lt;br>&lt;/b>&lt;font color=&quot;#000080&quot;>&lt;/font>&lt;/div>&lt;/html>"/></leaf>
<leaf><attribute name="name" value="obsolescence reason specification"/><attribute name="entity" value="http://purl.obolibrary.org/obo/IAO_0000225"/><attribute name="tooltip" value="&lt;html>&lt;div style=&quot;font-size:11;width:500&quot;>&lt;b>Class: http://purl.obolibrary.org/obo/IAO_0000225&lt;br>&lt;/b>&lt;b>&lt;i>obsolescence reason specification&lt;/i>&lt;/b>&lt;i>&lt;div style=&quot;margin-left:5px;margin-top:2px;margin-bottom:2px&quot;>The reason for which a term has been deprecated. The allowed values come from an enumerated list of predefined terms. See the specification of these instances for more detailed definitions of each enumerated value.&lt;/div>&lt;/i>&lt;b>super:  data about an ontology part&lt;br>&lt;/b>&lt;font color=&quot;#000080&quot;>(&lt;i>and&lt;/i>&lt;br>&amp;nbsp;(&lt;i>or&lt;/i>&amp;nbsp;(&lt;i>has&lt;/i>&amp;nbsp;failed&amp;middot;exploratory&amp;middot;term)&amp;nbsp;(&lt;i>has&lt;/i>&amp;nbsp;other)&lt;br>&amp;nbsp;&amp;nbsp;(&lt;i>has&lt;/i>&amp;nbsp;terms&amp;middot;merged)&amp;nbsp;(&lt;i>has&lt;/i>&amp;nbsp;placeholder&amp;middot;removed)&lt;br>&amp;nbsp;&amp;nbsp;(&lt;i>has&lt;/i>&amp;nbsp;term&amp;middot;split)&amp;nbsp;(&lt;i>has&lt;/i>&amp;nbsp;term&amp;middot;imported))&lt;br>&amp;nbsp;data&amp;middot;about&amp;middot;an&amp;middot;ontology&amp;middot;part)&lt;br>&lt;/font>&lt;hr>&lt;i>definition editor&lt;/i>: PERSON: Alan Ruttenberg&lt;br>&lt;i>definition editor&lt;/i>: PERSON: Melanie Courtot&lt;br>&lt;i>editor note&lt;/i>: The creation of this class has been inspired in part by Werner Ceusters' paper, Applying evolutionary terminology auditing to the Gene Ontology.&lt;br>&lt;i>definition&lt;/i>: The reason for which a term has been deprecated. The allowed values come from an enumerated list of predefined terms. See the specification of these instances for more detailed definitions of each enumerated value.&lt;br>&lt;i>has curation status&lt;/i>: has curation status&lt;br>&lt;i>editor preferred term&lt;/i>: obsolescence reason specification&lt;br>&lt;/div>&lt;/html>"/></leaf>
<leaf><attribute name="name" value="DbXref"/><attribute name="entity" value="http://www.geneontology.org/formats/oboInOwl#DbXref"/><attribute name="tooltip" value="&lt;html>&lt;div style=&quot;font-size:11;width:500&quot;>&lt;b>Class: http://www.geneontology.org/formats/oboInOwl#DbXref&lt;br>&lt;/b>&lt;i>&lt;/i>&lt;b>super:  data about an ontology part&lt;br>&lt;/b>&lt;font color=&quot;#000080&quot;>&lt;/font>&lt;/div>&lt;/html>"/></leaf>
<leaf><attribute name="name" value="curation status specification"/><attribute name="entity" value="http://purl.obolibrary.org/obo/IAO_0000078"/><attribute name="tooltip" value="&lt;html>&lt;div style=&quot;font-size:11;width:500&quot;>&lt;b>Class: http://purl.obolibrary.org/obo/IAO_0000078&lt;br>&lt;/b>&lt;b>&lt;i>curation status specification&lt;/i>&lt;/b>&lt;i>&lt;div style=&quot;margin-left:5px;margin-top:2px;margin-bottom:2px&quot;>The curation status of the term. The allowed values come from an enumerated list of predefined terms. See the specification of these instances for more detailed definitions of each enumerated value.&lt;/div>&lt;/i>&lt;b>super:  data about an ontology part&lt;br>&lt;/b>&lt;font color=&quot;#000080&quot;>(&lt;i>and&lt;/i>&lt;br>&amp;nbsp;(&lt;i>or&lt;/i>&amp;nbsp;(&lt;i>has&lt;/i>&amp;nbsp;metadata&amp;middot;incomplete)&lt;br>&amp;nbsp;&amp;nbsp;(&lt;i>has&lt;/i>&amp;nbsp;ready&amp;middot;for&amp;middot;release)&amp;nbsp;(&lt;i>has&lt;/i>&amp;nbsp;uncurated)&lt;br>&amp;nbsp;&amp;nbsp;(&lt;i>has&lt;/i>&amp;nbsp;metadata&amp;middot;complete)&amp;nbsp;(&lt;i>has&lt;/i>&amp;nbsp;placeholder)&lt;br>&amp;nbsp;&amp;nbsp;(&lt;i>has&lt;/i>&amp;nbsp;pending&amp;middot;final&amp;middot;vetting)&lt;br>&amp;nbsp;&amp;nbsp;(&lt;i>has&lt;/i>&amp;nbsp;example&amp;middot;to&amp;middot;be&amp;middot;eventually&amp;middot;removed))&lt;br>&amp;nbsp;data&amp;middot;about&amp;middot;an&amp;middot;ontology&amp;middot;part)&lt;br>&lt;/font>&lt;hr>&lt;i>definition source&lt;/i>: OBI_0000266&lt;br>&lt;i>definition source&lt;/i>: GROUP:OBI:&lt;http://purl.obolibrary.org/obo/obi>&lt;br>&lt;i>definition editor&lt;/i>: PERSON:Bill Bug&lt;br>&lt;i>editor note&lt;/i>: Better to represent curation as a process with parts and then relate labels to that process (in IAO meeting)&lt;br>&lt;i>definition&lt;/i>: The curation status of the term. The allowed values come from an enumerated list of predefined terms. See the specification of these instances for more detailed definitions of each enumerated value.&lt;br>&lt;i>has curation status&lt;/i>: has curation status&lt;br>&lt;i>editor preferred term&lt;/i>: curation status specification&lt;br>&lt;/div>&lt;/html>"/></leaf>
<leaf><attribute name="name" value="denotator type"/><attribute name="entity" value="http://purl.obolibrary.org/obo/IAO_0000409"/><attribute name="tooltip" value="&lt;html>&lt;div style=&quot;font-size:11;width:500&quot;>&lt;b>Class: http://purl.obolibrary.org/obo/IAO_0000409&lt;br>&lt;/b>&lt;b>&lt;i>denotator type&lt;/i>&lt;/b>&lt;i>&lt;div style=&quot;margin-left:5px;margin-top:2px;margin-bottom:2px&quot;>A denotator type indicates how a term should be interpreted from an ontological perspective.&lt;/div>&lt;/i>&lt;b>super:  data about an ontology part&lt;br>&lt;/b>&lt;font color=&quot;#000080&quot;>(&lt;i>and&lt;/i>&amp;nbsp;data&amp;middot;about&amp;middot;an&amp;middot;ontology&amp;middot;part&lt;br>&amp;nbsp;(&lt;i>or&lt;/i>&amp;nbsp;(&lt;i>has&lt;/i>&amp;nbsp;named&amp;middot;class&amp;middot;expression)&lt;br>&amp;nbsp;&amp;nbsp;(&lt;i>has&lt;/i>&amp;nbsp;defined&amp;middot;class)&amp;nbsp;(&lt;i>has&lt;/i>&amp;nbsp;universal)))&lt;br>&lt;/font>&lt;hr>&lt;i>definition source&lt;/i>: Barry Smith, Werner Ceusters&lt;br>&lt;i>definition editor&lt;/i>: Alan Ruttenberg&lt;br>&lt;i>definition&lt;/i>: A denotator type indicates how a term should be interpreted from an ontological perspective.&lt;br>&lt;i>example of usage&lt;/i>: The Basic Formal Ontology ontology makes a distinction between Universals and defined classes, where the formal are &quot;natural kinds&quot; and the latter arbitrary collections of entities.&lt;br>&lt;/div>&lt;/html>"/></leaf>
<leaf><attribute name="name" value="Synonym"/><attribute name="entity" value="http://www.geneontology.org/formats/oboInOwl#Synonym"/><attribute name="tooltip" value="&lt;html>&lt;div style=&quot;font-size:11;width:500&quot;>&lt;b>Class: http://www.geneontology.org/formats/oboInOwl#Synonym&lt;br>&lt;/b>&lt;i>&lt;/i>&lt;b>super:  data about an ontology part&lt;br>&lt;/b>&lt;font color=&quot;#000080&quot;>&lt;/font>&lt;/div>&lt;/html>"/></leaf>
</branch>
<leaf><attribute name="name" value="preclinical finding"/><attribute name="entity" value="http://purl.obolibrary.org/obo/OGMS_0000019"/><attribute name="tooltip" value="&lt;html>&lt;div style=&quot;font-size:11;width:500&quot;>&lt;b>Class: http://purl.obolibrary.org/obo/OGMS_0000019&lt;br>&lt;/b>&lt;b>&lt;i>preclinical finding&lt;/i>&lt;/b>&lt;i>&lt;div style=&quot;margin-left:5px;margin-top:2px;margin-bottom:2px&quot;>A representation of a bodily feature of a patient that is (1) recorded by a clinician because the feature is hypothesized to be of clinical significance and (2) refers to features obtaining in the patient prior to their becoming detectable in a clinical history taking or physical examination.&lt;/div>&lt;/i>&lt;b>super:  data item&lt;br>&lt;/b>&lt;font color=&quot;#000080&quot;>&lt;/font>&lt;hr>&lt;i>curator note&lt;/i>: creation date: 2009-06-23T10:22:44Z&lt;br>&lt;i>definition source&lt;/i>: http://ontology.buffalo.edu/medo/Disease_and_Diagnosis.pdf&lt;br>&lt;i>definition editor&lt;/i>: Albert Goldfain&lt;br>&lt;i>definition&lt;/i>: A representation of a bodily feature of a patient that is (1) recorded by a clinician because the feature is hypothesized to be of clinical significance and (2) refers to features obtaining in the patient prior to their becoming detectable in a clinical history taking or physical examination.&lt;br>&lt;/div>&lt;/html>"/></leaf>
</branch>
</branch>
<leaf><attribute name="name" value="normal value"/><attribute name="entity" value="http://purl.obolibrary.org/obo/OGMS_0000074"/><attribute name="tooltip" value="&lt;html>&lt;div style=&quot;font-size:11;width:500&quot;>&lt;b>Class: http://purl.obolibrary.org/obo/OGMS_0000074&lt;br>&lt;/b>&lt;b>&lt;i>normal value&lt;/i>&lt;/b>&lt;i>&lt;div style=&quot;margin-left:5px;margin-top:2px;margin-bottom:2px&quot;>A value for a quality reported in a lab report and asserted by the testing lab or the kit manufacturer to be normal based on a statistical treatment of values from a reference population.&lt;/div>&lt;/i>&lt;b>super:  generically_dependent_continuant&lt;br>&lt;/b>&lt;font color=&quot;#000080&quot;>&lt;/font>&lt;hr>&lt;i>curator note&lt;/i>: creation date: 2009-06-26T10:31:34Z&lt;br>&lt;i>definition source&lt;/i>: http://ontology.buffalo.edu/medo/Disease_and_Diagnosis.pdf&lt;br>&lt;i>definition editor&lt;/i>: Albert Goldfain&lt;br>&lt;i>definition&lt;/i>: A value for a quality reported in a lab report and asserted by the testing lab or the kit manufacturer to be normal based on a statistical treatment of values from a reference population.&lt;br>&lt;/div>&lt;/html>"/></leaf>
</branch>
</branch>
<branch><attribute name="name" value="independent_continuant(3)"/><attribute name="entity" value="http://www.ifomis.org/bfo/1.1/snap#IndependentContinuant"/><attribute name="tooltip" value="&lt;html>&lt;div style=&quot;font-size:11;width:500&quot;>&lt;b>Class: http://www.ifomis.org/bfo/1.1/snap#IndependentContinuant&lt;br>&lt;/b>&lt;b>&lt;i>independent_continuant&lt;/i>&lt;/b>&lt;i>&lt;div style=&quot;margin-left:5px;margin-top:2px;margin-bottom:2px&quot;>Synonyms: substantial entity; Examples: an organism, a heart, a leg, a person, a symphony orchestra, a chair, the bottom right portion of a human torso, the lawn and atmosphere in front of our building; Definition: A continuant [snap:Continuant] that is a bearer of quality [snap:Quality] and realizable entity [snap:RealizableEntity] entities, in which other entities inhere and which itself cannot inhere in anything.&lt;/div>&lt;/i>&lt;b>super:  continuant&lt;br>&lt;/b>&lt;font color=&quot;#000080&quot;>(&lt;i>and&lt;/i>&amp;nbsp;continuant&amp;nbsp;(&lt;i>or&lt;/i>&amp;nbsp;material_entity&amp;nbsp;object_boundary&amp;nbsp;site)&lt;br>&amp;nbsp;(&lt;i>disjoint-with&lt;/i>&amp;nbsp;spatial_region&amp;nbsp;dependent_continuant))&lt;br>&lt;/font>&lt;/div>&lt;/html>"/>
<branch><attribute name="name" value="material_entity(6)"/><attribute name="entity" value="http://www.ifomis.org/bfo/1.1/snap#MaterialEntity"/><attribute name="tooltip" value="&lt;html>&lt;div style=&quot;font-size:11;width:500&quot;>&lt;b>Class: http://www.ifomis.org/bfo/1.1/snap#MaterialEntity&lt;br>&lt;/b>&lt;b>&lt;i>material_entity&lt;/i>&lt;/b>&lt;i>&lt;div style=&quot;margin-left:5px;margin-top:2px;margin-bottom:2px&quot;>Examples: collection of random bacteria, a chair, dorsal surface of the body; Definition: An independent continuant [snap:IndependentContinuant] that is spatially extended whose identity is independent of that of other entities and can be maintained through time. Note: Material entity [snap:MaterialEntity] subsumes object [snap:Object], fiat object part [snap:FiatObjectPart], and object aggregate [snap:ObjectAggregate], which assume a three level theory of granularity, which is inadequate for some domains, such as biology.&lt;/div>&lt;/i>&lt;b>super:  independent_continuant&lt;br>&lt;/b>&lt;font color=&quot;#000080&quot;>(&lt;i>and&lt;/i>&amp;nbsp;independent_continuant&amp;nbsp;(&lt;i>or&lt;/i>&amp;nbsp;fiat_object_part&amp;nbsp;object&amp;nbsp;object_aggregate))&lt;br>&lt;/font>&lt;/div>&lt;/html>"/>
<leaf><attribute name="name" value="pathological formation"/><attribute name="entity" value="http://purl.obolibrary.org/obo/OGMS_0000077"/><attribute name="tooltip" value="&lt;html>&lt;div style=&quot;font-size:11;width:500&quot;>&lt;b>Class: http://purl.obolibrary.org/obo/OGMS_0000077&lt;br>&lt;/b>&lt;b>&lt;i>pathological formation&lt;/i>&lt;/b>&lt;i>&lt;div style=&quot;margin-left:5px;margin-top:2px;margin-bottom:2px&quot;>TODO: Define, relate to disorder, and place in the OGMS hierarchy.&lt;/div>&lt;/i>&lt;b>super:  material_entity&lt;br>&lt;/b>&lt;font color=&quot;#000080&quot;>&lt;/font>&lt;hr>&lt;i>curator note&lt;/i>: creation date: 2009-07-13T02:14:59Z&lt;br>&lt;i>definition source&lt;/i>: http://ontology.buffalo.edu/bio/ISMB/ISMB_Bio-ontologies.pdf&lt;br>&lt;i>definition editor&lt;/i>: Albert Goldfain&lt;br>&lt;i>definition&lt;/i>: TODO: Define, relate to disorder, and place in the OGMS hierarchy.&lt;br>&lt;/div>&lt;/html>"/></leaf>
<branch><attribute name="name" value="object_aggregate(1)"/><attribute name="entity" value="http://www.ifomis.org/bfo/1.1/snap#ObjectAggregate"/><attribute name="tooltip" value="&lt;html>&lt;div style=&quot;font-size:11;width:500&quot;>&lt;b>Class: http://www.ifomis.org/bfo/1.1/snap#ObjectAggregate&lt;br>&lt;/b>&lt;b>&lt;i>object_aggregate&lt;/i>&lt;/b>&lt;i>&lt;div style=&quot;margin-left:5px;margin-top:2px;margin-bottom:2px&quot;>Synonyms: substance aggregate; Examples: a heap of stones, a group of commuters on the subway, a collection of random bacteria, a flock of geese, the patients in a hospital; Definition: A material entity [snap:MaterialEntity] that is a mereological sum of separate object [snap:Object] entities and possesses non-connected boundaries.&lt;/div>&lt;/i>&lt;b>super:  material_entity&lt;br>&lt;/b>&lt;font color=&quot;#000080&quot;>(&lt;i>and&lt;/i>&amp;nbsp;material_entity&amp;nbsp;(&lt;i>disjoint-with&lt;/i>&amp;nbsp;object&amp;nbsp;fiat_object_part))&lt;br>&lt;/font>&lt;/div>&lt;/html>"/>
<leaf><attribute name="name" value="organism population"/><attribute name="entity" value="http://purl.obolibrary.org/obo/OGMS_0000084"/><attribute name="tooltip" value="&lt;html>&lt;div style=&quot;font-size:11;width:500&quot;>&lt;b>Class: http://purl.obolibrary.org/obo/OGMS_0000084&lt;br>&lt;/b>&lt;b>&lt;i>organism population&lt;/i>&lt;/b>&lt;i>&lt;div style=&quot;margin-left:5px;margin-top:2px;margin-bottom:2px&quot;>An aggregate of organisms of the same type.&lt;/div>&lt;/i>&lt;b>super:  object_aggregate&lt;br>&lt;/b>&lt;font color=&quot;#000080&quot;>&lt;/font>&lt;hr>&lt;i>curator note&lt;/i>: creation date: 2009-11-24T04:51:11Z&lt;br>&lt;i>definition source&lt;/i>: http://code.google.com/p/ogms/issues/detail?id=33&lt;br>&lt;i>definition editor&lt;/i>: Albert Goldfain&lt;br>&lt;i>definition&lt;/i>: An aggregate of organisms of the same type.&lt;br>&lt;/div>&lt;/html>"/></leaf>
</branch>
<leaf><attribute name="name" value="portion of pathological body substance"/><attribute name="entity" value="http://purl.obolibrary.org/obo/OGMS_0000079"/><attribute name="tooltip" value="&lt;html>&lt;div style=&quot;font-size:11;width:500&quot;>&lt;b>Class: http://purl.obolibrary.org/obo/OGMS_0000079&lt;br>&lt;/b>&lt;b>&lt;i>portion of pathological body substance&lt;/i>&lt;/b>&lt;i>&lt;div style=&quot;margin-left:5px;margin-top:2px;margin-bottom:2px&quot;>TODO: Define, relate to disorder, and place in the OGMS hierarchy.&lt;/div>&lt;/i>&lt;b>super:  material_entity&lt;br>&lt;/b>&lt;font color=&quot;#000080&quot;>&lt;/font>&lt;hr>&lt;i>curator note&lt;/i>: creation date: 2009-07-13T02:15:17Z&lt;br>&lt;i>definition source&lt;/i>: http://ontology.buffalo.edu/bio/ISMB/ISMB_Bio-ontologies.pdf&lt;br>&lt;i>definition editor&lt;/i>: Albert Goldfain&lt;br>&lt;i>definition&lt;/i>: TODO: Define, relate to disorder, and place in the OGMS hierarchy.&lt;br>&lt;/div>&lt;/html>"/></leaf>
<leaf><attribute name="name" value="pathological anatomical structure"/><attribute name="entity" value="http://purl.obolibrary.org/obo/OGMS_0000078"/><attribute name="tooltip" value="&lt;html>&lt;div style=&quot;font-size:11;width:500&quot;>&lt;b>Class: http://purl.obolibrary.org/obo/OGMS_0000078&lt;br>&lt;/b>&lt;b>&lt;i>pathological anatomical structure&lt;/i>&lt;/b>&lt;i>&lt;div style=&quot;margin-left:5px;margin-top:2px;margin-bottom:2px&quot;>An anatomical structure (FMA) is pathological whenever (1) it has come into being as a result of changes in some pre-existing canonical anatomical structure, (2) through processes other than the expression of the normal complement of genes of an organism of the given type, and (3) is predisposed to have health-related consequences for the organism in question manifested by symptoms and signs.&lt;/div>&lt;/i>&lt;b>super:  material_entity&lt;br>&lt;/b>&lt;font color=&quot;#000080&quot;>&lt;/font>&lt;hr>&lt;i>curator note&lt;/i>: creation date: 2009-07-13T02:14:05Z&lt;br>&lt;i>definition source&lt;/i>: http://ontology.buffalo.edu/bio/ISMB/ISMB_Bio-ontologies.pdf&lt;br>&lt;i>definition editor&lt;/i>: Albert Goldfain&lt;br>&lt;i>definition&lt;/i>: An anatomical structure (FMA) is pathological whenever (1) it has come into being as a result of changes in some pre-existing canonical anatomical structure, (2) through processes other than the expression of the normal complement of genes of an organism of the given type, and (3) is predisposed to have health-related consequences for the organism in question manifested by symptoms and signs.&lt;br>&lt;/div>&lt;/html>"/></leaf>
<leaf><attribute name="name" value="object"/><attribute name="entity" value="http://www.ifomis.org/bfo/1.1/snap#Object"/><attribute name="tooltip" value="&lt;html>&lt;div style=&quot;font-size:11;width:500&quot;>&lt;b>Class: http://www.ifomis.org/bfo/1.1/snap#Object&lt;br>&lt;/b>&lt;b>&lt;i>object&lt;/i>&lt;/b>&lt;i>&lt;div style=&quot;margin-left:5px;margin-top:2px;margin-bottom:2px&quot;>Synonyms: substance; Examples: an organism, a heart, a chair, a lung, an apple; Definition: A material entity [snap:MaterialEntity] that is spatially extended, maximally self-connected and self-contained (the parts of a substance are not separated from each other by spatial gaps) and possesses an internal unity. The identity of substantial object [snap:Object] entities is independent of that of other entities and can be maintained through time.&lt;/div>&lt;/i>&lt;b>super:  material_entity&lt;br>&lt;/b>&lt;font color=&quot;#000080&quot;>(&lt;i>and&lt;/i>&amp;nbsp;material_entity&amp;nbsp;(&lt;i>disjoint-with&lt;/i>&amp;nbsp;fiat_object_part&amp;nbsp;object_aggregate))&lt;br>&lt;/font>&lt;/div>&lt;/html>"/></leaf>
<branch><attribute name="name" value="fiat_object_part(1)"/><attribute name="entity" value="http://www.ifomis.org/bfo/1.1/snap#FiatObjectPart"/><attribute name="tooltip" value="&lt;html>&lt;div style=&quot;font-size:11;width:500&quot;>&lt;b>Class: http://www.ifomis.org/bfo/1.1/snap#FiatObjectPart&lt;br>&lt;/b>&lt;b>&lt;i>fiat_object_part&lt;/i>&lt;/b>&lt;i>&lt;div style=&quot;margin-left:5px;margin-top:2px;margin-bottom:2px&quot;>Synonyms: fiat substance part; Examples: upper and lower lobes of the left lung, the dorsal and ventral surfaces of the body, the east side of Saarbruecken, the lower right portion of a human torso; Definition: A material entity [snap:MaterialEntity] that is part of an object [snap:Object] but is not demarcated by any physical discontinuities.&lt;/div>&lt;/i>&lt;b>super:  material_entity&lt;br>&lt;/b>&lt;font color=&quot;#000080&quot;>(&lt;i>and&lt;/i>&amp;nbsp;material_entity&amp;nbsp;(&lt;i>disjoint-with&lt;/i>&amp;nbsp;object_aggregate&amp;nbsp;object&amp;nbsp;site))&lt;br>&lt;/font>&lt;/div>&lt;/html>"/>
<branch><attribute name="name" value="disorder(2)"/><attribute name="entity" value="http://purl.obolibrary.org/obo/OGMS_0000045"/><attribute name="tooltip" value="&lt;html>&lt;div style=&quot;font-size:11;width:500&quot;>&lt;b>Class: http://purl.obolibrary.org/obo/OGMS_0000045&lt;br>&lt;/b>&lt;b>&lt;i>disorder&lt;/i>&lt;/b>&lt;i>&lt;div style=&quot;margin-left:5px;margin-top:2px;margin-bottom:2px&quot;>A causally relatively isolated combination of physical components that is (a) clinically abnormal and (b) maximal, in the sense that it is not part of some larger such combination. Disorders are the physical basis of disease.&lt;/div>&lt;/i>&lt;b>super:  fiat_object_part&lt;br>&lt;/b>&lt;font color=&quot;#000080&quot;>&lt;/font>&lt;hr>&lt;i>curator note&lt;/i>: creation date: 2009-06-23T11:39:44Z&lt;br>&lt;i>definition source&lt;/i>: http://ontology.buffalo.edu/medo/Disease_and_Diagnosis.pdf&lt;br>&lt;i>definition editor&lt;/i>: Albert Goldfain&lt;br>&lt;i>definition&lt;/i>: A causally relatively isolated combination of physical components that is (a) clinically abnormal and (b) maximal, in the sense that it is not part of some larger such combination. Disorders are the physical basis of disease.&lt;br>&lt;/div>&lt;/html>"/>
<leaf><attribute name="name" value="epigenetic disorder"/><attribute name="entity" value="http://purl.obolibrary.org/obo/OGMS_0000046"/><attribute name="tooltip" value="&lt;html>&lt;div style=&quot;font-size:11;width:500&quot;>&lt;b>Class: http://purl.obolibrary.org/obo/OGMS_0000046&lt;br>&lt;/b>&lt;b>&lt;i>epigenetic disorder&lt;/i>&lt;/b>&lt;i>&lt;div style=&quot;margin-left:5px;margin-top:2px;margin-bottom:2px&quot;>A disorder whose etiology involves (1) a modification to the patient's genomic DNA which leads to alterations in the normal expression pattern of the genome, but is (2) not a change in the nucleotide sequence.&lt;/div>&lt;/i>&lt;b>super:  disorder&lt;br>&lt;/b>&lt;font color=&quot;#000080&quot;>&lt;/font>&lt;hr>&lt;i>curator note&lt;/i>: creation date: 2009-06-23T11:40:27Z&lt;br>&lt;i>definition source&lt;/i>: http://ontology.buffalo.edu/medo/Disease_and_Diagnosis.pdf&lt;br>&lt;i>definition editor&lt;/i>: Albert Goldfain&lt;br>&lt;i>definition&lt;/i>: A disorder whose etiology involves (1) a modification to the patient's genomic DNA which leads to alterations in the normal expression pattern of the genome, but is (2) not a change in the nucleotide sequence.&lt;br>&lt;/div>&lt;/html>"/></leaf>
<branch><attribute name="name" value="genetic disorder(2)"/><attribute name="entity" value="http://purl.obolibrary.org/obo/OGMS_0000047"/><attribute name="tooltip" value="&lt;html>&lt;div style=&quot;font-size:11;width:500&quot;>&lt;b>Class: http://purl.obolibrary.org/obo/OGMS_0000047&lt;br>&lt;/b>&lt;b>&lt;i>genetic disorder&lt;/i>&lt;/b>&lt;i>&lt;div style=&quot;margin-left:5px;margin-top:2px;margin-bottom:2px&quot;>A disorder whose etiology involves an abnormality in the nucleotide sequence of an organism's genome.&lt;/div>&lt;/i>&lt;b>super:  disorder&lt;br>&lt;/b>&lt;font color=&quot;#000080&quot;>&lt;/font>&lt;hr>&lt;i>curator note&lt;/i>: creation date: 2009-06-23T11:41:14Z&lt;br>&lt;i>definition source&lt;/i>: http://ontology.buffalo.edu/medo/Disease_and_Diagnosis.pdf&lt;br>&lt;i>definition editor&lt;/i>: Albert Goldfain&lt;br>&lt;i>definition&lt;/i>: A disorder whose etiology involves an abnormality in the nucleotide sequence of an organism's genome.&lt;br>&lt;/div>&lt;/html>"/>
<leaf><attribute name="name" value="constitutional genetic disorder"/><attribute name="entity" value="http://purl.obolibrary.org/obo/OGMS_0000051"/><attribute name="tooltip" value="&lt;html>&lt;div style=&quot;font-size:11;width:500&quot;>&lt;b>Class: http://purl.obolibrary.org/obo/OGMS_0000051&lt;br>&lt;/b>&lt;b>&lt;i>constitutional genetic disorder&lt;/i>&lt;/b>&lt;i>&lt;div style=&quot;margin-left:5px;margin-top:2px;margin-bottom:2px&quot;>A genetic disorder inherited during conception that is borne by all cells in the organism.&lt;/div>&lt;/i>&lt;b>super:  genetic disorder&lt;br>&lt;/b>&lt;font color=&quot;#000080&quot;>&lt;/font>&lt;hr>&lt;i>curator note&lt;/i>: creation date: 2009-06-23T11:43:44Z&lt;br>&lt;i>definition source&lt;/i>: http://ontology.buffalo.edu/medo/Disease_and_Diagnosis.pdf&lt;br>&lt;i>definition editor&lt;/i>: Albert Goldfain&lt;br>&lt;i>definition&lt;/i>: A genetic disorder inherited during conception that is borne by all cells in the organism.&lt;br>&lt;/div>&lt;/html>"/></leaf>
<leaf><attribute name="name" value="acquired genetic disorder"/><attribute name="entity" value="http://purl.obolibrary.org/obo/OGMS_0000050"/><attribute name="tooltip" value="&lt;html>&lt;div style=&quot;font-size:11;width:500&quot;>&lt;b>Class: http://purl.obolibrary.org/obo/OGMS_0000050&lt;br>&lt;/b>&lt;b>&lt;i>acquired genetic disorder&lt;/i>&lt;/b>&lt;i>&lt;div style=&quot;margin-left:5px;margin-top:2px;margin-bottom:2px&quot;>A genetic disorder acquired by a single cell in an organism that leads to a population of cells within the organism bearing the disorder.&lt;/div>&lt;/i>&lt;b>super:  genetic disorder&lt;br>&lt;/b>&lt;font color=&quot;#000080&quot;>&lt;/font>&lt;hr>&lt;i>curator note&lt;/i>: creation date: 2009-06-23T11:43:09Z&lt;br>&lt;i>definition source&lt;/i>: http://ontology.buffalo.edu/medo/Disease_and_Diagnosis.pdf&lt;br>&lt;i>definition editor&lt;/i>: Albert Goldfain&lt;br>&lt;i>definition&lt;/i>: A genetic disorder acquired by a single cell in an organism that leads to a population of cells within the organism bearing the disorder.&lt;br>&lt;/div>&lt;/html>"/></leaf>
</branch>
</branch>
</branch>
</branch>
<leaf><attribute name="name" value="site"/><attribute name="entity" value="http://www.ifomis.org/bfo/1.1/snap#Site"/><attribute name="tooltip" value="&lt;html>&lt;div style=&quot;font-size:11;width:500&quot;>&lt;b>Class: http://www.ifomis.org/bfo/1.1/snap#Site&lt;br>&lt;/b>&lt;b>&lt;i>site&lt;/i>&lt;/b>&lt;i>&lt;div style=&quot;margin-left:5px;margin-top:2px;margin-bottom:2px&quot;>Comment: An instance of Site [snap:Site] is a mixture of independent continuant [snap:IndependentContinuant] entities which act as surrounding environments for other independent continuant [snap:IndependentContinuant] entities, most importantly for instances of object [snap:Object]. A site [snap:Site] is typically made of object [snap:Object] or fiat object part [snap:FiatObjectPart] entities and a surrounding medium in which is found an object [snap:Object] occupying the site [snap:Site]. Independent continuant [snap:IndependentContinuant] entities may be associated with others (which, then, are site [snap:Site] entities) through a relation of &quot;occupation&quot;. That relation is connected to, but distinct from, the relation of spatial location. Site [snap:Site] entities are not to be confused with spatial region [snap:SpatialRegion] entities. In BFO, site [snap:Site] allows for a so-called relational view of space which is different from the view corresponding to the class spatial region [snap:SpatialRegion] (see the comment on this class).; Examples: a particular room in a particular hospital, Maria's nostril or her intestines for a variety of bacteria.; Definition: An independent continuant [snap:IndependentContinuant] consisting of a characteristic spatial shape in relation to some arrangement of other continuant [snap:Continuant] entities and of the medium which is enclosed in whole or in part by this characteristic spatial shape. Site [snap:Site] entities are entities that can be occupied by other continuant [snap:Continuant] entities.&lt;/div>&lt;/i>&lt;b>super:  independent_continuant&lt;br>&lt;/b>&lt;font color=&quot;#000080&quot;>(&lt;i>and&lt;/i>&amp;nbsp;independent_continuant&lt;br>&amp;nbsp;(&lt;i>disjoint-with&lt;/i>&amp;nbsp;object_aggregate&amp;nbsp;fiat_object_part&amp;nbsp;object&amp;nbsp;material_entity))&lt;br>&lt;/font>&lt;/div>&lt;/html>"/></leaf>
<leaf><attribute name="name" value="object_boundary"/><attribute name="entity" value="http://www.ifomis.org/bfo/1.1/snap#ObjectBoundary"/><attribute name="tooltip" value="&lt;html>&lt;div style=&quot;font-size:11;width:500&quot;>&lt;b>Class: http://www.ifomis.org/bfo/1.1/snap#ObjectBoundary&lt;br>&lt;/b>&lt;b>&lt;i>object_boundary&lt;/i>&lt;/b>&lt;i>&lt;div style=&quot;margin-left:5px;margin-top:2px;margin-bottom:2px&quot;>Definition: An independent continuant [snap:IndependentContinuant] that is a lower dimensional part of a spatial entity, normally a closed two-dimensional surface. Boundaries are those privileged parts of object [snap:Object] entities that exist at exactly the point where the object [snap:Object] is separated off from the rest of the existing entities in the world.; Examples: the surface of the skin, the surface of the earth, the surface of the interior of the stomach, the outer surface of a cell or cell wall; Comment: Boundaries are theoretically difficult entities to account for, however the intuitive notion of a physical boundary as a surface of some sort (whether inside or outside of a thing) will generally serve as a good guide for the use of this universal.; Synonyms: substance boundary&lt;/div>&lt;/i>&lt;b>super:  independent_continuant&lt;br>&lt;/b>&lt;font color=&quot;#000080&quot;>(&lt;i>and&lt;/i>&amp;nbsp;independent_continuant&lt;br>&amp;nbsp;(&lt;i>disjoint-with&lt;/i>&amp;nbsp;object_aggregate&amp;nbsp;object&amp;nbsp;fiat_object_part&amp;nbsp;site&amp;nbsp;material_entity))&lt;br>&lt;/font>&lt;/div>&lt;/html>"/></leaf>
</branch>
</branch>
<branch><attribute name="name" value="_undefined primitive term(3)"/><attribute name="entity" value="http://purl.obolibrary.org/obo/OGMS_0000067"/><attribute name="tooltip" value="&lt;html>&lt;div style=&quot;font-size:11;width:500&quot;>&lt;b>Class: http://purl.obolibrary.org/obo/OGMS_0000067&lt;br>&lt;/b>&lt;b>&lt;i>_undefined primitive term&lt;/i>&lt;/b>&lt;i>&lt;br>&lt;/i>&lt;b>super:  entity&lt;br>&lt;/b>&lt;font color=&quot;#000080&quot;>&lt;/font>&lt;hr>&lt;i>curator note&lt;/i>: creation date: 2009-06-23T11:58:22Z&lt;br>&lt;i>definition editor&lt;/i>: Albert Goldfain&lt;br>&lt;/div>&lt;/html>"/>
<leaf><attribute name="name" value="physical basis"/><attribute name="entity" value="http://purl.obolibrary.org/obo/OGMS_0000070"/><attribute name="tooltip" value="&lt;html>&lt;div style=&quot;font-size:11;width:500&quot;>&lt;b>Class: http://purl.obolibrary.org/obo/OGMS_0000070&lt;br>&lt;/b>&lt;b>&lt;i>physical basis&lt;/i>&lt;/b>&lt;i>&lt;br>&lt;/i>&lt;b>super:  _undefined primitive term&lt;br>&lt;/b>&lt;font color=&quot;#000080&quot;>&lt;/font>&lt;hr>&lt;i>curator note&lt;/i>: creation date: 2009-06-23T12:00:09Z&lt;br>&lt;i>definition editor&lt;/i>: Albert Goldfain&lt;br>&lt;/div>&lt;/html>"/></leaf>
<leaf><attribute name="name" value="clinically abnormal"/><attribute name="entity" value="http://purl.obolibrary.org/obo/OGMS_0000069"/><attribute name="tooltip" value="&lt;html>&lt;div style=&quot;font-size:11;width:500&quot;>&lt;b>Class: http://purl.obolibrary.org/obo/OGMS_0000069&lt;br>&lt;/b>&lt;b>&lt;i>clinically abnormal&lt;/i>&lt;/b>&lt;i>&lt;br>&lt;/i>&lt;b>super:  _undefined primitive term&lt;br>&lt;/b>&lt;font color=&quot;#000080&quot;>&lt;/font>&lt;hr>&lt;i>curator note&lt;/i>: creation date: 2009-06-23T11:59:24Z&lt;br>&lt;i>definition editor&lt;/i>: Albert Goldfain&lt;br>&lt;/div>&lt;/html>"/></leaf>
<leaf><attribute name="name" value="realization"/><attribute name="entity" value="http://purl.obolibrary.org/obo/OGMS_0000071"/><attribute name="tooltip" value="&lt;html>&lt;div style=&quot;font-size:11;width:500&quot;>&lt;b>Class: http://purl.obolibrary.org/obo/OGMS_0000071&lt;br>&lt;/b>&lt;b>&lt;i>realization&lt;/i>&lt;/b>&lt;i>&lt;br>&lt;/i>&lt;b>super:  _undefined primitive term&lt;br>&lt;/b>&lt;font color=&quot;#000080&quot;>&lt;/font>&lt;hr>&lt;i>curator note&lt;/i>: creation date: 2009-06-23T12:00:39Z&lt;br>&lt;i>definition editor&lt;/i>: Albert Goldfain&lt;br>&lt;/div>&lt;/html>"/></leaf>
</branch>
</branch>
</tree> 